{ "compressionlevel":-1,
 "height":18,
 "infinite":false,
 "layers":[
        {
         "draworder":"topdown",
         "id":5,
         "name":"objects",
         "objects":[
                {
                 "height":31.3333333333333,
                 "id":3,
                 "name":"level3",
                 "properties":[
                        {
                         "name":"direction",
                         "type":"string",
                         "value":"down"
                        }, 
                        {
                         "name":"marioSpawnX",
                         "type":"int",
                         "value":16
                        }, 
                        {
                         "name":"marioSpawnY",
                         "type":"int",
                         "value":16
                        }],
                 "rotation":0,
                 "type":"portal",
                 "visible":true,
                 "width":16,
                 "x":2376.66666666667,
                 "y":0.833333333333333
                }, 
                {
                 "height":14,
                 "id":5,
                 "name":"player",
                 "rotation":0,
                 "type":"player",
                 "visible":true,
                 "width":8,
                 "x":9,
                 "y":48.6666666666667
                }, 
                {
                 "height":8,
                 "id":7,
                 "name":"box",
                 "properties":[
                        {
                         "name":"content",
                         "type":"string",
                         "value":"mushroom"
                        }],
                 "rotation":0,
                 "type":"box",
                 "visible":true,
                 "width":8,
                 "x":216,
                 "y":64.3333333333333
                }, 
                {
                 "height":8,
                 "id":8,
                 "name":"goomba",
                 "rotation":0,
                 "type":"goomba",
                 "visible":true,
                 "width":8,
                 "x":169.666666666667,
                 "y":47.6666666666667
                }, 
                {
                 "height":8,
                 "id":9,
                 "name":"box",
                 "properties":[
                        {
                         "name":"content",
                         "type":"string",
                         "value":"coin"
                        }],
                 "rotation":0,
                 "type":"box",
                 "visible":true,
                 "width":8,
                 "x":124,
                 "y":40
                }, 
                {
                 "height":8,
                 "id":10,
                 "name":"box",
                 "properties":[
                        {
                         "name":"content",
                         "type":"string",
                         "value":"rotatingCoin"
                        }],
                 "rotation":0,
                 "type":"box",
                 "visible":true,
                 "width":8,
                 "x":140,
                 "y":40
                }, 
                {
                 "height":8,
                 "id":11,
                 "name":"box",
                 "properties":[
                        {
                         "name":"content",
                         "type":"string",
                         "value":"coin"
                        }],
                 "rotation":0,
                 "type":"box",
                 "visible":true,
                 "width":8,
                 "x":156,
                 "y":40
                }, 
                {
                 "height":8,
                 "id":12,
                 "name":"brick",
                 "rotation":0,
                 "type":"brick",
                 "visible":true,
                 "width":8,
                 "x":132,
                 "y":40
                }, 
                {
                 "height":8,
                 "id":13,
                 "name":"brick",
                 "rotation":0,
                 "type":"brick",
                 "visible":true,
                 "width":8,
                 "x":148,
                 "y":40
                }, 
                {
                 "height":8,
                 "id":14,
                 "name":"collectible",
                 "properties":[
                        {
                         "name":"kindOfCollectible",
                         "type":"string",
                         "value":"coin2"
                        }],
                 "rotation":0,
                 "type":"collectible",
                 "visible":true,
                 "width":8,
                 "x":725.333333333333,
                 "y":75.6666666666667
                }, 
                {
                 "height":8,
                 "id":15,
                 "name":"collectible",
                 "properties":[
                        {
                         "name":"kindOfCollectible",
                         "type":"string",
                         "value":"coin2"
                        }],
                 "rotation":0,
                 "type":"collectible",
                 "visible":true,
                 "width":8,
                 "x":725.333333333333,
                 "y":67.6666666666667
                }, 
                {
                 "height":8,
                 "id":16,
                 "name":"collectible",
                 "properties":[
                        {
                         "name":"kindOfCollectible",
                         "type":"string",
                         "value":"coin2"
                        }],
                 "rotation":0,
                 "type":"collectible",
                 "visible":true,
                 "width":8,
                 "x":725.333333333333,
                 "y":59.6666666666667
                }, 
                {
                 "height":8,
                 "id":17,
                 "name":"collectible",
                 "properties":[
                        {
                         "name":"kindOfCollectible",
                         "type":"string",
                         "value":"coin2"
                        }],
                 "rotation":0,
                 "type":"collectible",
                 "visible":true,
                 "width":8,
                 "x":725.333333333333,
                 "y":83.6666666666667
                }, 
                {
                 "height":8,
                 "id":21,
                 "name":"goomba",
                 "rotation":0,
                 "type":"goomba",
                 "visible":true,
                 "width":8,
                 "x":438,
                 "y":31.3333333333333
                }, 
                {
                 "height":8,
                 "id":22,
                 "name":"goomba",
                 "rotation":0,
                 "type":"goomba",
                 "visible":true,
                 "width":8,
                 "x":423.333333333333,
                 "y":31.3333333333333
                }, 
                {
                 "height":8,
                 "id":23,
                 "name":"collectible",
                 "properties":[
                        {
                         "name":"kindOfCollectible",
                         "type":"string",
                         "value":"coin2"
                        }],
                 "rotation":0,
                 "type":"collectible",
                 "visible":true,
                 "width":8,
                 "x":593,
                 "y":50.99985
                }, 
                {
                 "height":8,
                 "id":24,
                 "name":"collectible",
                 "properties":[
                        {
                         "name":"kindOfCollectible",
                         "type":"string",
                         "value":"coin2"
                        }],
                 "rotation":0,
                 "type":"collectible",
                 "visible":true,
                 "width":8,
                 "x":593,
                 "y":58.99985
                }, 
                {
                 "height":8,
                 "id":25,
                 "name":"collectible",
                 "properties":[
                        {
                         "name":"kindOfCollectible",
                         "type":"string",
                         "value":"coin2"
                        }],
                 "rotation":0,
                 "type":"collectible",
                 "visible":true,
                 "width":8,
                 "x":593,
                 "y":67.00015
                }, 
                {
                 "height":8,
                 "id":26,
                 "name":"brick",
                 "rotation":0,
                 "type":"brick",
                 "visible":true,
                 "width":8,
                 "x":489.333333333333,
                 "y":24
                }, 
                {
                 "height":8,
                 "id":27,
                 "name":"brick",
                 "rotation":0,
                 "type":"brick",
                 "visible":true,
                 "width":8,
                 "x":497.333333333333,
                 "y":24
                }, 
                {
                 "height":8,
                 "id":28,
                 "name":"brick",
                 "rotation":0,
                 "type":"brick",
                 "visible":true,
                 "width":8,
                 "x":505.333333333333,
                 "y":24
                }, 
                {
                 "height":8,
                 "id":29,
                 "name":"brick",
                 "rotation":0,
                 "type":"brick",
                 "visible":true,
                 "width":8,
                 "x":521.333333333333,
                 "y":24
                }, 
                {
                 "height":8,
                 "id":30,
                 "name":"brick",
                 "rotation":0,
                 "type":"brick",
                 "visible":true,
                 "width":8,
                 "x":513.333333333333,
                 "y":24
                }, 
                {
                 "height":8,
                 "id":31,
                 "name":"brick",
                 "rotation":0,
                 "type":"brick",
                 "visible":true,
                 "width":8,
                 "x":529.333333333333,
                 "y":24
                }, 
                {
                 "height":8,
                 "id":32,
                 "name":"goomba",
                 "rotation":0,
                 "type":"goomba",
                 "visible":true,
                 "width":8,
                 "x":522.666666666667,
                 "y":5
                }, 
                {
                 "height":8,
                 "id":33,
                 "name":"goomba",
                 "rotation":0,
                 "type":"goomba",
                 "visible":true,
                 "width":8,
                 "x":541.666666666667,
                 "y":5
                }, 
                {
                 "height":8,
                 "id":39,
                 "name":"box",
                 "properties":[
                        {
                         "name":"content",
                         "type":"string",
                         "value":"rotatingCoin"
                        }],
                 "rotation":0,
                 "type":"box",
                 "visible":true,
                 "width":8,
                 "x":808.666666666667,
                 "y":22
                }, 
                {
                 "height":8,
                 "id":40,
                 "name":"box",
                 "properties":[
                        {
                         "name":"content",
                         "type":"string",
                         "value":"flower"
                        }],
                 "rotation":0,
                 "type":"box",
                 "visible":true,
                 "width":8,
                 "x":856.333333333333,
                 "y":80.6666666666667
                }, 
                {
                 "height":5,
                 "id":41,
                 "name":"platformMovingUpAndDown",
                 "rotation":0,
                 "type":"platformMovingUpAndDown",
                 "visible":true,
                 "width":24,
                 "x":928,
                 "y":71.5
                }, 
                {
                 "height":5,
                 "id":42,
                 "name":"platformMovingUpAndDown",
                 "rotation":0,
                 "type":"platformMovingUpAndDown",
                 "visible":true,
                 "width":24,
                 "x":972.333333333333,
                 "y":89.5
                }, 
                {
                 "height":8,
                 "id":43,
                 "name":"collectible",
                 "properties":[
                        {
                         "name":"kindOfCollectible",
                         "type":"string",
                         "value":"coin2"
                        }],
                 "rotation":0,
                 "type":"collectible",
                 "visible":true,
                 "width":8,
                 "x":1087,
                 "y":31.6666666666667
                }, 
                {
                 "height":8,
                 "id":44,
                 "name":"collectible",
                 "properties":[
                        {
                         "name":"kindOfCollectible",
                         "type":"string",
                         "value":"coin2"
                        }],
                 "rotation":0,
                 "type":"collectible",
                 "visible":true,
                 "width":8,
                 "x":1096.33333333333,
                 "y":31.6666666666667
                }, 
                {
                 "height":8,
                 "id":45,
                 "name":"collectible",
                 "properties":[
                        {
                         "name":"kindOfCollectible",
                         "type":"string",
                         "value":"coin2"
                        }],
                 "rotation":0,
                 "type":"collectible",
                 "visible":true,
                 "width":8,
                 "x":1106,
                 "y":31.3333333333333
                }, 
                {
                 "height":8,
                 "id":46,
                 "name":"goomba",
                 "rotation":0,
                 "type":"goomba",
                 "visible":true,
                 "width":8,
                 "x":1152.3335,
                 "y":32
                }, 
                {
                 "height":8,
                 "id":47,
                 "name":"goomba",
                 "rotation":0,
                 "type":"goomba",
                 "visible":true,
                 "width":8,
                 "x":1128.6665,
                 "y":32
                }, 
                {
                 "height":8,
                 "id":48,
                 "name":"goomba",
                 "rotation":0,
                 "type":"goomba",
                 "visible":true,
                 "width":8,
                 "x":1098,
                 "y":17
                }, 
                {
                 "height":5,
                 "id":49,
                 "name":"platformMovingLeftAndRight",
                 "rotation":0,
                 "type":"platformMovingLeftAndRight",
                 "visible":true,
                 "width":24,
                 "x":1309.33333333333,
                 "y":40.8333333333333
                }, 
                {
                 "height":8,
                 "id":50,
                 "name":"box",
                 "properties":[
                        {
                         "name":"content",
                         "type":"string",
                         "value":"mushroom"
                        }],
                 "rotation":0,
                 "type":"box",
                 "visible":true,
                 "width":8,
                 "x":1368,
                 "y":95
                }, 
                {
                 "height":8,
                 "id":51,
                 "name":"brick",
                 "rotation":0,
                 "type":"brick",
                 "visible":true,
                 "width":8,
                 "x":1400.33333333333,
                 "y":104.333333333333
                }, 
                {
                 "height":8,
                 "id":52,
                 "name":"brick",
                 "rotation":0,
                 "type":"brick",
                 "visible":true,
                 "width":8,
                 "x":1408.33333333333,
                 "y":104.333333333333
                }, 
                {
                 "height":8,
                 "id":53,
                 "name":"brick",
                 "rotation":0,
                 "type":"brick",
                 "visible":true,
                 "width":8,
                 "x":1416.33333333333,
                 "y":104.333333333333
                }, 
                {
                 "height":8,
                 "id":60,
                 "name":"goomba",
                 "rotation":0,
                 "type":"goomba",
                 "visible":true,
                 "width":8,
                 "x":1257.167,
                 "y":4.5
                }, 
                {
                 "height":8,
                 "id":61,
                 "name":"goomba",
                 "rotation":0,
                 "type":"goomba",
                 "visible":true,
                 "width":8,
                 "x":1276.167,
                 "y":4.5
                }, 
                {
                 "height":8,
                 "id":62,
                 "name":"box",
                 "properties":[
                        {
                         "name":"content",
                         "type":"string",
                         "value":"rotatingCoin"
                        }],
                 "rotation":0,
                 "type":"box",
                 "visible":true,
                 "width":8,
                 "x":1219.66666666667,
                 "y":23.3333333333333
                }, 
                {
                 "height":8,
                 "id":63,
                 "name":"box",
                 "properties":[
                        {
                         "name":"content",
                         "type":"string",
                         "value":"rotatingCoin"
                        }],
                 "rotation":0,
                 "type":"box",
                 "visible":true,
                 "width":8,
                 "x":1227.66666666667,
                 "y":23.3333333333333
                }, 
                {
                 "height":8,
                 "id":64,
                 "name":"box",
                 "properties":[
                        {
                         "name":"content",
                         "type":"string",
                         "value":"rotatingCoin"
                        }],
                 "rotation":0,
                 "type":"box",
                 "visible":true,
                 "width":8,
                 "x":1235.66666666667,
                 "y":23.3333333333333
                }, 
                {
                 "height":8,
                 "id":65,
                 "name":"box",
                 "properties":[
                        {
                         "name":"content",
                         "type":"string",
                         "value":"rotatingCoin"
                        }],
                 "rotation":0,
                 "type":"box",
                 "visible":true,
                 "width":8,
                 "x":1243.66666666667,
                 "y":23.3333333333333
                }, 
                {
                 "height":8,
                 "id":66,
                 "name":"box",
                 "properties":[
                        {
                         "name":"content",
                         "type":"string",
                         "value":"rotatingCoin"
                        }],
                 "rotation":0,
                 "type":"box",
                 "visible":true,
                 "width":8,
                 "x":1251.66666666667,
                 "y":23.3333333333333
                }, 
                {
                 "height":8,
                 "id":67,
                 "name":"box",
                 "properties":[
                        {
                         "name":"content",
                         "type":"string",
                         "value":"rotatingCoin"
                        }],
                 "rotation":0,
                 "type":"box",
                 "visible":true,
                 "width":8,
                 "x":1259.66666666667,
                 "y":23.3333333333333
                }, 
                {
                 "height":5,
                 "id":68,
                 "name":"platformMovingUpAndDown",
                 "rotation":0,
                 "type":"platformMovingUpAndDown",
                 "visible":true,
                 "width":24,
                 "x":1535.66666666667,
                 "y":57.5
                }, 
                {
                 "height":5,
                 "id":69,
                 "name":"platformMovingUpAndDown",
                 "rotation":0,
                 "type":"platformMovingUpAndDown",
                 "visible":true,
                 "width":24,
                 "x":1578,
                 "y":90.5
                }, 
                {
                 "height":5,
                 "id":70,
                 "name":"platformMovingLeftAndRight",
                 "rotation":0,
                 "type":"platformMovingLeftAndRight",
                 "visible":true,
                 "width":24,
                 "x":1624,
                 "y":74.1666666666667
                }, 
                {
                 "height":8,
                 "id":71,
                 "name":"box",
                 "properties":[
                        {
                         "name":"content",
                         "type":"string",
                         "value":"mushroom"
                        }],
                 "rotation":0,
                 "type":"box",
                 "visible":true,
                 "width":8,
                 "x":1800.66666666667,
                 "y":80.6666666666667
                }, 
                {
                 "height":5,
                 "id":72,
                 "name":"platformMovingLeftAndRight",
                 "rotation":0,
                 "type":"platformMovingLeftAndRight",
                 "visible":true,
                 "width":24,
                 "x":1897,
                 "y":57.8333333333333
                }, 
                {
                 "height":8,
                 "id":73,
                 "name":"collectible",
                 "properties":[
                        {
                         "name":"kindOfCollectible",
                         "type":"string",
                         "value":"coin2"
                        }],
                 "rotation":0,
                 "type":"collectible",
                 "visible":true,
                 "width":8,
                 "x":2033.33333333333,
                 "y":101.333333333333
                }, 
                {
                 "height":8,
                 "id":74,
                 "name":"collectible",
                 "properties":[
                        {
                         "name":"kindOfCollectible",
                         "type":"string",
                         "value":"coin2"
                        }],
                 "rotation":0,
                 "type":"collectible",
                 "visible":true,
                 "width":8,
                 "x":2033.33333333333,
                 "y":117.333333333333
                }, 
                {
                 "height":8,
                 "id":75,
                 "name":"collectible",
                 "properties":[
                        {
                         "name":"kindOfCollectible",
                         "type":"string",
                         "value":"coin2"
                        }],
                 "rotation":0,
                 "type":"collectible",
                 "visible":true,
                 "width":8,
                 "x":2033.33333333333,
                 "y":85.3333333333333
                }, 
                {
                 "height":8,
                 "id":76,
                 "name":"collectible",
                 "properties":[
                        {
                         "name":"kindOfCollectible",
                         "type":"string",
                         "value":"coin2"
                        }],
                 "rotation":0,
                 "type":"collectible",
                 "visible":true,
                 "width":8,
                 "x":2033.33333333333,
                 "y":69.3333333333333
                }, 
                {
                 "height":8,
                 "id":77,
                 "name":"collectible",
                 "properties":[
                        {
                         "name":"kindOfCollectible",
                         "type":"string",
                         "value":"coin2"
                        }],
                 "rotation":0,
                 "type":"collectible",
                 "visible":true,
                 "width":8,
                 "x":2033.33333333333,
                 "y":53.3333333333333
                }, 
                {
                 "height":8,
                 "id":78,
                 "name":"collectible",
                 "properties":[
                        {
                         "name":"kindOfCollectible",
                         "type":"string",
                         "value":"coin2"
                        }],
                 "rotation":0,
                 "type":"collectible",
                 "visible":true,
                 "width":8,
                 "x":1680,
                 "y":97
                }, 
                {
                 "height":8,
                 "id":79,
                 "name":"collectible",
                 "properties":[
                        {
                         "name":"kindOfCollectible",
                         "type":"string",
                         "value":"coin2"
                        }],
                 "rotation":0,
                 "type":"collectible",
                 "visible":true,
                 "width":8,
                 "x":1728.66666666667,
                 "y":62.3333333333333
                }, 
                {
                 "height":8,
                 "id":80,
                 "name":"collectible",
                 "properties":[
                        {
                         "name":"kindOfCollectible",
                         "type":"string",
                         "value":"coin2"
                        }],
                 "rotation":0,
                 "type":"collectible",
                 "visible":true,
                 "width":8,
                 "x":1760.66666666667,
                 "y":30.6666666666667
                }, 
                {
                 "height":8,
                 "id":81,
                 "name":"collectible",
                 "properties":[
                        {
                         "name":"kindOfCollectible",
                         "type":"string",
                         "value":"coin2"
                        }],
                 "rotation":0,
                 "type":"collectible",
                 "visible":true,
                 "width":8,
                 "x":1772.33333333333,
                 "y":30.6666666666667
                }, 
                {
                 "height":8,
                 "id":82,
                 "name":"collectible",
                 "properties":[
                        {
                         "name":"kindOfCollectible",
                         "type":"string",
                         "value":"coin2"
                        }],
                 "rotation":0,
                 "type":"collectible",
                 "visible":true,
                 "width":8,
                 "x":1848.33333333333,
                 "y":31
                }, 
                {
                 "height":8,
                 "id":83,
                 "name":"collectible",
                 "properties":[
                        {
                         "name":"kindOfCollectible",
                         "type":"string",
                         "value":"coin2"
                        }],
                 "rotation":0,
                 "type":"collectible",
                 "visible":true,
                 "width":8,
                 "x":2181.83333333333,
                 "y":40.0000166666667
                }, 
                {
                 "height":8,
                 "id":84,
                 "name":"collectible",
                 "properties":[
                        {
                         "name":"kindOfCollectible",
                         "type":"string",
                         "value":"coin2"
                        }],
                 "rotation":0,
                 "type":"collectible",
                 "visible":true,
                 "width":8,
                 "x":2191.16333333333,
                 "y":40.0000166666667
                }, 
                {
                 "height":8,
                 "id":85,
                 "name":"collectible",
                 "properties":[
                        {
                         "name":"kindOfCollectible",
                         "type":"string",
                         "value":"coin2"
                        }],
                 "rotation":0,
                 "type":"collectible",
                 "visible":true,
                 "width":8,
                 "x":2200.83333333333,
                 "y":39.6666166666667
                }, 
                {
                 "height":8,
                 "id":86,
                 "name":"goomba",
                 "rotation":0,
                 "type":"goomba",
                 "visible":true,
                 "width":8,
                 "x":2192.83333333333,
                 "y":25.3333166666667
                }, 
                {
                 "height":8,
                 "id":87,
                 "name":"goomba",
                 "rotation":0,
                 "type":"goomba",
                 "visible":true,
                 "width":8,
                 "x":2120.33333333333,
                 "y":71.6666666666667
                }, 
                {
                 "height":8,
                 "id":88,
                 "name":"goomba",
                 "rotation":0,
                 "type":"goomba",
                 "visible":true,
                 "width":8,
                 "x":2065,
                 "y":95
                }, 
                {
                 "height":5,
                 "id":89,
                 "name":"platformMovingUpAndDown",
                 "rotation":0,
                 "type":"platformMovingUpAndDown",
                 "visible":true,
                 "width":24,
                 "x":2281.66666666667,
                 "y":102.166666666667
                }, 
                {
                 "height":5,
                 "id":90,
                 "name":"platformMovingLeftAndRight",
                 "rotation":0,
                 "type":"platformMovingLeftAndRight",
                 "visible":true,
                 "width":24,
                 "x":2315.16666666667,
                 "y":40.8333333333333
                }, 
                {
                 "height":5,
                 "id":91,
                 "name":"platformMovingUpAndDown",
                 "rotation":0,
                 "type":"platformMovingUpAndDown",
                 "visible":true,
                 "width":24,
                 "x":313.666666666667,
                 "y":67.8333333333333
                }, 
                {
                 "height":16,
                 "id":92,
                 "name":"exit",
                 "properties":[
                        {
                         "name":"direction",
                         "type":"string",
                         "value":"none"
                        }, 
                        {
                         "name":"marioSpawnX",
                         "type":"int",
                         "value":0
                        }, 
                        {
                         "name":"marioSpawnY",
                         "type":"int",
                         "value":0
                        }],
                 "rotation":0,
                 "type":"portal",
                 "visible":true,
                 "width":16,
                 "x":2376.5,
                 "y":120
                }, 
                {
                 "height":16,
                 "id":93,
                 "name":"kappa",
                 "rotation":0,
                 "type":"kappa",
                 "visible":true,
                 "width":8,
                 "x":409.5,
                 "y":27.5
                }, 
                {
                 "height":16,
                 "id":94,
                 "name":"kappa",
                 "rotation":0,
                 "type":"kappa",
                 "visible":true,
                 "width":8,
                 "x":1509,
                 "y":34
                }, 
                {
                 "height":16,
                 "id":95,
                 "name":"kappa",
                 "rotation":0,
                 "type":"kappa",
                 "visible":true,
                 "width":8,
                 "x":2212.5,
                 "y":50.5
                }, 
                {
                 "height":16,
                 "id":96,
                 "name":"kappa",
                 "rotation":0,
                 "type":"kappa",
                 "visible":true,
                 "width":8,
                 "x":156.5,
                 "y":52.5
                }],
         "opacity":1,
         "type":"objectgroup",
         "visible":true,
         "x":0,
         "y":0
        }, 
        {
         "data":[0, 0, 0, 0, 0, 0, 0, 0, 0, 0, 0, 0, 0, 0, 0, 0, 0, 0, 0, 0, 0, 0, 0, 0, 0, 0, 0, 0, 0, 0, 0, 0, 0, 0, 0, 0, 0, 0, 0, 0, 0, 0, 0, 0, 0, 0, 0, 0, 0, 0, 0, 0, 0, 0, 0, 0, 0, 0, 0, 0, 0, 0, 0, 0, 0, 0, 0, 0, 0, 0, 0, 0, 0, 0, 0, 0, 0, 0, 0, 0, 0, 0, 0, 0, 0, 0, 0, 0, 0, 0, 0, 0, 0, 0, 0, 0, 0, 0, 0, 0, 0, 0, 0, 0, 0, 0, 0, 0, 0, 0, 0, 0, 0, 0, 0, 0, 0, 0, 0, 0, 0, 0, 0, 0, 0, 0, 0, 0, 0, 0, 0, 0, 0, 0, 0, 0, 0, 0, 0, 0, 0, 0, 0, 0, 0, 0, 0, 0, 0, 0, 0, 0, 0, 0, 0, 0, 0, 0, 0, 0, 0, 0, 0, 0, 0, 0, 0, 0, 0, 0, 0, 0, 0, 0, 0, 0, 0, 0, 0, 0, 0, 0, 0, 0, 0, 0, 0, 0, 0, 0, 0, 0, 0, 0, 0, 0, 0, 0, 0, 0, 0, 0, 0, 0, 0, 0, 0, 0, 0, 0, 0, 0, 0, 0, 0, 0, 0, 0, 0, 0, 0, 0, 0, 0, 0, 0, 0, 0, 0, 0, 0, 0, 0, 0, 0, 0, 0, 0, 0, 0, 0, 0, 0, 0, 0, 0, 0, 0, 0, 0, 0, 0, 0, 0, 0, 0, 0, 0, 0, 0, 0, 0, 0, 0, 0, 0, 0, 0, 0, 0, 0, 0, 0, 0, 0, 0, 0, 0, 0, 0, 0, 0, 0, 0, 0, 0, 0, 0, 0, 0, 0, 0, 0, 0, 0, 0, 0, 0, 0, 33,
            0, 0, 0, 0, 0, 0, 0, 0, 0, 0, 0, 0, 0, 0, 0, 0, 0, 0, 0, 0, 0, 0, 0, 0, 0, 0, 0, 0, 0, 0, 0, 0, 0, 0, 0, 0, 0, 0, 0, 0, 0, 0, 0, 0, 0, 0, 0, 0, 0, 0, 0, 0, 0, 0, 0, 0, 0, 0, 0, 0, 0, 0, 0, 0, 0, 0, 0, 0, 0, 0, 0, 0, 0, 0, 0, 0, 0, 0, 0, 0, 0, 0, 0, 0, 0, 0, 0, 0, 0, 0, 0, 0, 0, 0, 0, 0, 0, 0, 0, 0, 0, 0, 0, 0, 0, 0, 0, 0, 0, 0, 0, 0, 0, 0, 0, 0, 0, 0, 0, 0, 0, 0, 0, 0, 0, 0, 0, 0, 0, 0, 0, 0, 0, 0, 0, 0, 0, 0, 0, 0, 0, 0, 0, 0, 0, 0, 0, 0, 0, 0, 0, 0, 0, 0, 0, 0, 0, 0, 0, 0, 0, 0, 0, 0, 0, 0, 0, 0, 0, 0, 0, 0, 0, 0, 0, 0, 0, 0, 0, 0, 0, 0, 0, 0, 0, 0, 0, 0, 0, 0, 0, 0, 0, 0, 0, 0, 0, 0, 0, 0, 0, 0, 0, 0, 0, 0, 0, 0, 0, 0, 0, 0, 0, 0, 0, 0, 0, 0, 0, 0, 0, 0, 0, 0, 0, 0, 0, 0, 0, 0, 0, 0, 0, 0, 0, 0, 0, 0, 0, 0, 0, 0, 0, 0, 0, 0, 0, 0, 0, 0, 0, 0, 0, 0, 0, 0, 0, 0, 0, 0, 0, 0, 0, 0, 0, 0, 0, 0, 0, 0, 0, 0, 0, 0, 0, 0, 0, 0, 0, 0, 0, 0, 0, 0, 0, 0, 0, 0, 0, 0, 0, 0, 0, 0, 0, 0, 0, 0, 0, 33,
            0, 0, 0, 0, 0, 0, 0, 0, 0, 0, 0, 0, 0, 0, 0, 0, 0, 0, 0, 0, 0, 0, 0, 0, 0, 0, 0, 0, 0, 0, 0, 0, 0, 0, 0, 0, 0, 0, 0, 0, 0, 0, 0, 0, 0, 0, 0, 0, 0, 0, 0, 0, 0, 0, 0, 0, 0, 0, 0, 0, 0, 0, 0, 0, 0, 0, 0, 0, 0, 0, 0, 0, 0, 0, 0, 0, 0, 0, 0, 0, 0, 0, 0, 0, 0, 0, 0, 0, 0, 0, 0, 0, 0, 0, 0, 0, 0, 0, 0, 0, 0, 0, 0, 0, 0, 0, 0, 0, 0, 0, 0, 0, 0, 0, 0, 0, 0, 0, 0, 0, 0, 0, 0, 0, 0, 0, 0, 0, 0, 0, 0, 0, 0, 0, 0, 0, 0, 0, 0, 0, 0, 0, 0, 0, 0, 0, 0, 0, 0, 0, 0, 0, 0, 0, 0, 0, 0, 0, 0, 0, 0, 0, 0, 0, 0, 0, 0, 0, 0, 0, 0, 0, 0, 0, 0, 0, 0, 0, 0, 0, 0, 0, 0, 0, 0, 0, 0, 0, 0, 0, 0, 0, 0, 0, 0, 0, 0, 0, 0, 0, 0, 0, 0, 0, 0, 0, 0, 0, 0, 0, 0, 0, 0, 0, 0, 0, 0, 0, 0, 0, 0, 0, 0, 0, 0, 0, 0, 0, 0, 0, 0, 0, 0, 0, 0, 0, 0, 0, 0, 0, 0, 0, 0, 0, 0, 0, 0, 0, 0, 0, 0, 0, 0, 0, 0, 0, 0, 0, 0, 0, 0, 0, 0, 0, 0, 0, 0, 0, 0, 0, 0, 0, 0, 0, 0, 0, 0, 0, 0, 0, 0, 0, 0, 0, 0, 0, 0, 0, 0, 0, 0, 0, 0, 0, 0, 0, 0, 49, 50, 33,
            0, 0, 0, 0, 0, 0, 0, 0, 0, 0, 0, 0, 0, 0, 0, 0, 0, 0, 0, 0, 0, 0, 0, 0, 0, 0, 0, 0, 0, 0, 0, 0, 0, 0, 0, 0, 0, 0, 0, 0, 0, 0, 0, 0, 0, 0, 0, 0, 0, 0, 0, 0, 0, 0, 0, 0, 0, 0, 0, 0, 0, 0, 0, 0, 0, 0, 0, 0, 0, 0, 0, 0, 0, 0, 0, 0, 0, 0, 0, 0, 0, 0, 0, 0, 0, 0, 0, 0, 0, 0, 0, 0, 0, 0, 0, 0, 0, 0, 0, 0, 0, 0, 0, 0, 0, 0, 0, 0, 0, 0, 0, 0, 0, 0, 0, 0, 0, 0, 0, 0, 0, 0, 0, 0, 0, 0, 0, 0, 0, 0, 0, 0, 0, 0, 0, 0, 0, 0, 0, 0, 0, 0, 0, 0, 0, 0, 0, 0, 0, 0, 0, 0, 0, 0, 0, 0, 0, 0, 0, 0, 0, 0, 0, 0, 0, 0, 0, 0, 0, 0, 0, 0, 0, 0, 0, 0, 0, 0, 0, 0, 0, 0, 0, 0, 0, 0, 0, 0, 0, 0, 0, 0, 0, 0, 0, 0, 0, 0, 0, 0, 0, 0, 0, 0, 0, 0, 0, 0, 0, 0, 0, 0, 0, 0, 0, 0, 0, 0, 0, 0, 0, 0, 0, 0, 0, 0, 0, 0, 0, 0, 0, 0, 0, 0, 0, 0, 0, 0, 0, 0, 0, 0, 0, 0, 0, 0, 0, 0, 0, 0, 0, 0, 0, 0, 0, 0, 0, 0, 0, 0, 0, 0, 0, 0, 0, 0, 0, 0, 0, 0, 0, 0, 0, 0, 0, 0, 0, 0, 0, 0, 0, 0, 0, 0, 0, 0, 0, 0, 0, 0, 0, 0, 0, 0, 0, 0, 0, 65, 66, 33,
            0, 0, 0, 0, 0, 0, 0, 0, 0, 0, 0, 0, 0, 0, 0, 0, 0, 0, 0, 0, 0, 0, 0, 0, 0, 0, 0, 0, 0, 0, 0, 0, 0, 0, 0, 0, 0, 0, 0, 0, 0, 0, 0, 0, 0, 0, 0, 0, 0, 0, 0, 0, 0, 0, 0, 0, 0, 0, 0, 0, 0, 0, 0, 0, 0, 0, 0, 0, 0, 0, 0, 0, 0, 0, 0, 0, 0, 0, 0, 0, 0, 0, 0, 0, 0, 0, 0, 0, 0, 0, 0, 0, 0, 0, 0, 0, 0, 0, 0, 0, 0, 0, 0, 0, 0, 0, 0, 0, 0, 0, 0, 0, 0, 0, 0, 0, 0, 0, 0, 0, 0, 0, 0, 0, 0, 0, 0, 0, 0, 0, 0, 0, 0, 0, 0, 0, 0, 0, 0, 0, 0, 0, 0, 0, 0, 0, 0, 0, 0, 0, 0, 0, 0, 0, 0, 0, 0, 0, 0, 0, 0, 0, 0, 0, 0, 0, 0, 0, 0, 0, 0, 0, 0, 0, 0, 0, 0, 0, 0, 0, 0, 0, 0, 0, 0, 0, 0, 0, 0, 0, 0, 0, 0, 0, 0, 0, 0, 0, 0, 0, 0, 0, 0, 0, 0, 0, 0, 0, 0, 0, 0, 0, 0, 0, 0, 0, 0, 0, 0, 0, 0, 0, 0, 0, 0, 0, 0, 0, 0, 0, 0, 0, 0, 0, 0, 0, 0, 0, 0, 0, 0, 0, 0, 0, 0, 0, 0, 0, 0, 0, 0, 0, 0, 0, 0, 0, 0, 0, 0, 0, 0, 0, 0, 0, 0, 0, 0, 0, 0, 0, 0, 0, 0, 0, 0, 0, 0, 0, 0, 0, 0, 0, 0, 0, 0, 0, 0, 0, 0, 0, 0, 0, 0, 0, 0, 0, 33, 34, 33, 33,
            0, 0, 0, 0, 0, 0, 0, 0, 0, 0, 0, 0, 0, 0, 0, 0, 0, 0, 0, 0, 0, 0, 0, 0, 0, 0, 0, 0, 0, 0, 0, 0, 0, 0, 0, 0, 0, 0, 0, 0, 0, 0, 0, 0, 0, 0, 0, 0, 0, 0, 0, 0, 0, 0, 0, 0, 0, 0, 0, 0, 0, 0, 0, 0, 0, 0, 0, 0, 0, 0, 0, 0, 0, 0, 0, 0, 0, 0, 0, 0, 0, 0, 0, 0, 0, 0, 0, 0, 0, 0, 0, 0, 0, 0, 0, 0, 0, 0, 0, 0, 0, 0, 0, 0, 0, 0, 0, 0, 0, 0, 0, 0, 0, 0, 0, 0, 0, 0, 0, 0, 0, 0, 0, 0, 0, 0, 0, 0, 0, 0, 0, 0, 0, 0, 0, 0, 0, 0, 0, 0, 0, 0, 0, 0, 0, 0, 0, 0, 0, 0, 0, 0, 0, 0, 0, 0, 0, 0, 0, 0, 0, 0, 0, 0, 0, 0, 0, 0, 0, 0, 0, 0, 0, 0, 0, 0, 0, 0, 0, 0, 0, 0, 0, 0, 0, 0, 0, 0, 0, 0, 0, 0, 0, 0, 0, 0, 0, 0, 0, 0, 0, 0, 0, 0, 0, 0, 0, 0, 0, 0, 0, 0, 0, 0, 0, 0, 0, 0, 0, 0, 0, 0, 0, 0, 0, 0, 0, 0, 0, 0, 0, 0, 0, 0, 0, 0, 0, 0, 0, 0, 0, 0, 0, 0, 0, 0, 0, 0, 0, 0, 0, 0, 0, 0, 0, 0, 0, 0, 0, 0, 0, 0, 0, 0, 0, 0, 0, 0, 0, 0, 0, 0, 0, 0, 0, 0, 0, 0, 0, 0, 0, 0, 0, 0, 0, 0, 0, 0, 0, 0, 0, 0, 0, 0, 0, 0, 0, 33, 34, 33,
            0, 0, 0, 0, 0, 0, 0, 0, 0, 0, 0, 0, 0, 0, 0, 0, 0, 0, 0, 0, 0, 0, 0, 0, 0, 0, 0, 0, 0, 0, 0, 0, 0, 0, 0, 0, 0, 0, 0, 0, 0, 0, 0, 0, 0, 0, 0, 0, 0, 0, 0, 0, 0, 0, 0, 0, 0, 0, 0, 0, 0, 0, 0, 0, 0, 0, 0, 0, 0, 0, 0, 0, 0, 0, 0, 0, 0, 0, 0, 0, 0, 0, 0, 0, 0, 0, 0, 0, 0, 0, 0, 0, 0, 0, 0, 0, 0, 0, 0, 0, 0, 0, 0, 0, 0, 0, 0, 0, 0, 0, 0, 0, 0, 0, 0, 0, 0, 0, 0, 0, 0, 0, 0, 0, 0, 0, 0, 0, 0, 0, 0, 0, 0, 0, 0, 0, 0, 0, 0, 0, 0, 0, 0, 0, 0, 0, 0, 0, 0, 0, 0, 0, 0, 0, 0, 0, 0, 0, 0, 0, 0, 0, 0, 0, 0, 0, 0, 0, 0, 0, 0, 0, 0, 0, 0, 0, 0, 0, 0, 0, 0, 0, 0, 0, 0, 0, 0, 0, 17, 17, 0, 0, 0, 0, 0, 0, 0, 0, 0, 0, 0, 0, 0, 0, 0, 0, 0, 0, 0, 0, 0, 0, 0, 0, 0, 0, 0, 0, 0, 0, 0, 0, 0, 0, 0, 0, 0, 0, 0, 0, 0, 0, 0, 0, 0, 0, 0, 0, 0, 0, 0, 0, 0, 0, 0, 0, 0, 0, 0, 0, 0, 0, 0, 0, 0, 0, 0, 0, 0, 0, 0, 0, 0, 0, 0, 0, 0, 0, 0, 0, 0, 0, 0, 0, 0, 0, 0, 0, 0, 0, 0, 25, 25, 25, 0, 0, 0, 0, 0, 0, 0, 0, 0, 0, 0, 0, 0, 33, 34, 33,
            0, 0, 0, 0, 0, 0, 0, 0, 0, 0, 0, 0, 0, 0, 0, 0, 0, 0, 0, 0, 0, 0, 0, 0, 0, 0, 0, 0, 0, 0, 0, 0, 0, 0, 0, 0, 0, 0, 0, 0, 0, 0, 0, 0, 0, 0, 4, 5, 5, 5, 5, 5, 5, 5, 5, 6, 0, 0, 0, 4, 5, 5, 5, 5, 5, 5, 5, 5, 6, 0, 0, 0, 0, 0, 0, 0, 0, 0, 0, 0, 0, 0, 0, 4, 5, 6, 0, 0, 0, 0, 0, 0, 0, 0, 0, 0, 0, 0, 4, 5, 5, 5, 5, 5, 6, 0, 0, 0, 0, 0, 0, 4, 5, 6, 0, 0, 0, 0, 0, 0, 0, 0, 0, 0, 0, 0, 0, 0, 0, 0, 0, 0, 4, 5, 5, 5, 5, 5, 5, 5, 5, 5, 5, 5, 6, 0, 0, 0, 0, 4, 5, 5, 5, 5, 5, 5, 5, 5, 5, 5, 5, 6, 0, 0, 0, 0, 0, 0, 0, 0, 0, 0, 0, 0, 0, 0, 0, 0, 0, 0, 0, 0, 0, 0, 0, 0, 0, 17, 17, 17, 0, 0, 0, 0, 0, 0, 0, 0, 0, 0, 0, 0, 0, 0, 0, 0, 0, 0, 0, 0, 0, 0, 0, 0, 0, 0, 0, 0, 4, 5, 5, 5, 5, 5, 6, 0, 0, 0, 0, 0, 4, 5, 6, 0, 0, 0, 0, 0, 0, 0, 0, 0, 0, 0, 0, 0, 27, 27, 27, 0, 0, 0, 0, 0, 0, 0, 0, 0, 0, 0, 0, 0, 0, 0, 0, 0, 0, 0, 0, 0, 0, 0, 0, 0, 0, 0, 0, 0, 0, 0, 0, 0, 0, 0, 0, 0, 0, 0, 0, 0, 0, 0, 0, 0, 0, 0, 0, 33, 34, 33,
            0, 0, 0, 0, 0, 0, 0, 0, 0, 0, 0, 0, 0, 0, 0, 0, 0, 0, 0, 0, 0, 0, 0, 0, 0, 0, 0, 0, 0, 0, 0, 0, 0, 0, 0, 0, 0, 0, 0, 0, 0, 0, 0, 0, 0, 0, 0, 0, 0, 0, 25, 25, 0, 0, 0, 0, 0, 0, 0, 0, 0, 0, 0, 25, 25, 0, 0, 0, 0, 0, 0, 0, 0, 0, 0, 0, 0, 0, 0, 0, 0, 0, 0, 0, 25, 0, 0, 0, 0, 0, 0, 0, 0, 0, 0, 0, 0, 0, 0, 0, 0, 25, 0, 0, 0, 0, 0, 0, 0, 0, 0, 0, 25, 0, 0, 0, 0, 0, 0, 0, 0, 0, 0, 0, 0, 0, 0, 0, 0, 0, 0, 0, 0, 0, 0, 0, 25, 25, 25, 25, 25, 0, 0, 0, 0, 0, 0, 0, 0, 0, 0, 0, 0, 25, 25, 25, 25, 25, 0, 0, 0, 0, 0, 0, 0, 0, 0, 0, 0, 0, 0, 0, 0, 0, 0, 0, 0, 0, 0, 0, 0, 0, 0, 0, 0, 0, 17, 17, 17, 17, 0, 0, 0, 0, 0, 0, 0, 0, 0, 0, 0, 0, 0, 0, 0, 0, 0, 0, 0, 0, 0, 0, 0, 0, 0, 0, 0, 0, 0, 0, 0, 25, 0, 0, 0, 0, 0, 0, 0, 0, 0, 25, 0, 0, 0, 0, 0, 0, 0, 0, 0, 0, 0, 0, 0, 0, 0, 0, 0, 0, 0, 0, 0, 0, 0, 0, 0, 0, 0, 0, 0, 0, 0, 0, 0, 0, 0, 0, 0, 0, 0, 0, 0, 0, 0, 0, 0, 0, 0, 0, 0, 0, 0, 0, 0, 0, 0, 0, 0, 0, 0, 0, 0, 0, 0, 0, 0, 33, 34, 33,
            0, 0, 0, 0, 0, 0, 0, 0, 0, 0, 0, 0, 0, 0, 4, 5, 5, 5, 5, 5, 5, 5, 6, 0, 0, 0, 0, 0, 0, 0, 0, 0, 0, 0, 0, 0, 0, 0, 0, 0, 0, 0, 0, 0, 0, 0, 0, 0, 0, 0, 25, 25, 0, 0, 0, 0, 0, 0, 0, 0, 0, 0, 0, 25, 25, 0, 0, 0, 0, 0, 0, 0, 0, 0, 0, 0, 0, 0, 0, 0, 0, 0, 0, 0, 25, 0, 0, 0, 0, 0, 0, 0, 0, 0, 0, 0, 0, 0, 0, 0, 0, 25, 0, 0, 0, 0, 0, 0, 0, 0, 0, 0, 25, 0, 0, 0, 0, 0, 0, 0, 0, 0, 0, 0, 0, 0, 0, 25, 25, 25, 0, 0, 0, 0, 0, 0, 25, 25, 25, 25, 25, 0, 0, 0, 0, 0, 0, 0, 0, 0, 0, 0, 0, 25, 25, 25, 25, 25, 0, 0, 0, 0, 0, 0, 0, 0, 0, 0, 0, 0, 0, 0, 0, 0, 0, 0, 0, 0, 0, 0, 0, 0, 0, 0, 0, 17, 17, 17, 17, 17, 0, 0, 0, 0, 0, 0, 0, 0, 0, 0, 0, 0, 0, 0, 0, 0, 0, 0, 0, 0, 0, 0, 0, 0, 0, 0, 0, 0, 0, 0, 0, 25, 0, 0, 0, 0, 0, 0, 0, 0, 0, 25, 0, 0, 0, 0, 0, 0, 0, 0, 0, 0, 0, 0, 0, 0, 0, 0, 0, 0, 0, 0, 0, 0, 0, 0, 0, 0, 0, 0, 0, 0, 0, 0, 0, 0, 0, 0, 0, 4, 5, 5, 5, 5, 5, 5, 5, 6, 0, 0, 0, 0, 0, 0, 0, 0, 0, 0, 0, 0, 0, 0, 0, 0, 0, 0, 0, 33, 34, 33,
            0, 0, 0, 0, 0, 0, 0, 0, 0, 0, 0, 0, 0, 0, 0, 0, 25, 0, 0, 0, 25, 0, 0, 0, 0, 0, 0, 0, 0, 0, 0, 0, 0, 4, 5, 6, 0, 0, 0, 0, 0, 0, 0, 0, 0, 0, 0, 0, 0, 0, 25, 25, 0, 0, 0, 0, 0, 0, 0, 0, 0, 0, 0, 25, 25, 0, 0, 0, 0, 0, 0, 0, 0, 0, 0, 0, 0, 0, 4, 5, 6, 0, 0, 0, 25, 0, 0, 0, 0, 0, 0, 0, 0, 0, 0, 0, 0, 0, 0, 0, 0, 25, 0, 0, 0, 0, 0, 0, 0, 0, 0, 0, 25, 0, 0, 0, 0, 0, 0, 0, 0, 0, 0, 0, 0, 0, 0, 0, 0, 0, 0, 0, 0, 0, 0, 0, 25, 25, 25, 25, 25, 0, 0, 0, 0, 0, 0, 0, 0, 0, 0, 0, 0, 25, 25, 25, 25, 25, 0, 0, 0, 0, 0, 0, 0, 0, 0, 0, 0, 0, 0, 0, 0, 0, 0, 0, 0, 0, 0, 0, 0, 0, 0, 0, 17, 17, 17, 17, 17, 17, 0, 0, 0, 0, 0, 0, 0, 0, 0, 0, 0, 0, 0, 0, 0, 0, 0, 0, 0, 0, 0, 0, 0, 0, 0, 0, 0, 0, 0, 0, 0, 25, 0, 0, 0, 0, 0, 0, 0, 0, 0, 25, 0, 0, 0, 0, 0, 0, 0, 0, 0, 0, 0, 0, 0, 0, 0, 0, 0, 0, 0, 0, 0, 0, 0, 0, 0, 0, 0, 0, 0, 0, 0, 0, 0, 0, 0, 0, 0, 0, 0, 25, 0, 0, 0, 25, 0, 0, 0, 0, 0, 0, 0, 0, 0, 0, 0, 0, 0, 0, 0, 0, 0, 0, 0, 0, 0, 33, 34, 33,
            0, 0, 0, 0, 0, 0, 0, 0, 0, 0, 0, 0, 0, 0, 0, 0, 25, 0, 0, 0, 25, 0, 0, 0, 0, 0, 0, 0, 0, 0, 0, 0, 0, 0, 25, 0, 0, 0, 0, 0, 0, 0, 0, 0, 0, 0, 0, 0, 0, 0, 25, 25, 0, 0, 0, 0, 0, 0, 0, 0, 0, 0, 0, 25, 25, 0, 0, 0, 0, 0, 0, 0, 0, 0, 0, 0, 0, 0, 0, 25, 0, 0, 0, 0, 25, 0, 0, 0, 0, 0, 0, 0, 0, 0, 0, 4, 5, 6, 0, 0, 0, 25, 0, 0, 0, 0, 0, 0, 0, 0, 0, 0, 25, 0, 0, 0, 0, 0, 0, 0, 0, 0, 0, 0, 0, 0, 0, 0, 0, 0, 0, 0, 0, 0, 0, 0, 25, 25, 25, 25, 25, 0, 0, 0, 0, 0, 0, 0, 0, 0, 0, 0, 0, 25, 25, 25, 25, 25, 0, 0, 0, 0, 0, 0, 0, 0, 0, 0, 0, 0, 0, 0, 0, 0, 0, 0, 0, 0, 0, 0, 0, 0, 0, 27, 27, 27, 27, 27, 27, 27, 0, 0, 0, 0, 0, 0, 0, 0, 0, 0, 0, 0, 0, 0, 0, 0, 0, 0, 0, 0, 0, 0, 0, 0, 0, 4, 5, 6, 0, 0, 0, 25, 0, 0, 0, 0, 0, 0, 0, 0, 0, 25, 0, 0, 0, 0, 0, 0, 0, 0, 0, 0, 0, 0, 0, 0, 0, 0, 0, 0, 0, 0, 0, 0, 0, 0, 0, 0, 0, 0, 0, 0, 0, 0, 0, 0, 0, 0, 0, 0, 0, 25, 0, 0, 0, 25, 0, 0, 0, 0, 0, 0, 0, 0, 0, 0, 0, 0, 0, 0, 0, 0, 0, 0, 0, 0, 0, 33, 34, 33,
            0, 0, 0, 0, 0, 0, 0, 0, 0, 0, 0, 0, 0, 0, 0, 0, 25, 0, 0, 0, 25, 0, 0, 0, 0, 0, 0, 0, 0, 0, 0, 0, 0, 0, 25, 0, 0, 0, 0, 0, 0, 0, 0, 0, 0, 0, 0, 0, 0, 0, 25, 25, 0, 0, 0, 0, 0, 0, 0, 0, 0, 0, 0, 25, 25, 0, 0, 0, 0, 0, 0, 0, 0, 4, 5, 6, 0, 0, 0, 25, 0, 0, 0, 0, 25, 0, 0, 0, 0, 0, 0, 0, 0, 0, 0, 0, 25, 0, 0, 0, 0, 25, 0, 0, 0, 0, 0, 0, 0, 0, 0, 0, 25, 0, 0, 0, 0, 0, 0, 0, 0, 0, 0, 0, 0, 0, 0, 0, 0, 0, 0, 0, 0, 0, 0, 0, 25, 25, 25, 25, 25, 0, 0, 0, 0, 0, 0, 0, 0, 0, 0, 0, 0, 25, 25, 25, 25, 25, 0, 0, 0, 0, 0, 0, 0, 0, 0, 0, 0, 0, 0, 0, 0, 0, 0, 0, 0, 0, 0, 0, 0, 0, 17, 17, 17, 17, 17, 17, 17, 17, 0, 0, 0, 0, 0, 0, 0, 0, 0, 0, 0, 0, 0, 0, 0, 0, 0, 0, 0, 0, 0, 0, 0, 0, 0, 0, 25, 0, 0, 0, 0, 25, 0, 0, 0, 0, 0, 0, 0, 0, 0, 25, 0, 0, 0, 0, 0, 0, 0, 0, 0, 0, 0, 0, 0, 0, 0, 0, 0, 0, 0, 0, 0, 0, 0, 0, 0, 0, 0, 0, 0, 0, 0, 0, 0, 0, 0, 0, 0, 0, 0, 25, 0, 0, 0, 25, 0, 0, 0, 0, 0, 0, 0, 0, 0, 0, 0, 0, 0, 0, 0, 0, 0, 0, 0, 0, 0, 33, 34, 33,
            0, 0, 0, 0, 0, 0, 0, 0, 4, 5, 5, 5, 5, 6, 0, 0, 25, 0, 0, 0, 25, 0, 0, 0, 4, 5, 5, 5, 5, 5, 6, 0, 0, 0, 25, 0, 0, 0, 0, 0, 0, 0, 0, 0, 0, 0, 0, 0, 0, 0, 25, 25, 0, 0, 0, 0, 0, 0, 0, 0, 0, 0, 0, 25, 25, 0, 0, 0, 0, 0, 0, 0, 0, 0, 25, 0, 0, 0, 0, 25, 0, 0, 0, 0, 25, 0, 0, 0, 0, 0, 0, 0, 0, 0, 0, 0, 25, 0, 0, 0, 0, 25, 0, 0, 0, 0, 0, 0, 0, 0, 0, 0, 25, 0, 0, 0, 0, 0, 0, 0, 0, 0, 0, 0, 0, 0, 0, 0, 0, 0, 0, 0, 0, 0, 0, 0, 25, 25, 25, 25, 25, 0, 0, 0, 0, 0, 0, 0, 0, 0, 0, 0, 0, 25, 25, 25, 25, 25, 0, 0, 0, 0, 0, 0, 0, 0, 0, 0, 0, 0, 0, 0, 0, 0, 0, 0, 0, 0, 0, 0, 0, 17, 17, 17, 17, 17, 17, 17, 17, 17, 0, 0, 0, 0, 0, 0, 0, 0, 0, 0, 0, 0, 0, 0, 0, 0, 0, 0, 0, 0, 0, 0, 0, 0, 0, 0, 25, 0, 0, 0, 0, 25, 0, 0, 0, 0, 0, 0, 0, 0, 0, 25, 0, 0, 0, 0, 0, 0, 0, 0, 0, 0, 0, 0, 0, 0, 0, 0, 0, 0, 0, 0, 0, 0, 0, 0, 0, 0, 0, 0, 0, 4, 5, 5, 5, 5, 6, 0, 0, 0, 0, 25, 0, 0, 0, 25, 0, 0, 0, 0, 0, 0, 0, 0, 0, 0, 0, 0, 0, 0, 0, 0, 0, 0, 0, 0, 0, 33, 34, 33,
            0, 0, 0, 0, 0, 0, 0, 0, 0, 0, 25, 25, 0, 0, 0, 0, 25, 0, 0, 0, 25, 0, 0, 0, 0, 0, 0, 25, 0, 0, 0, 0, 0, 0, 25, 0, 0, 0, 0, 0, 0, 0, 0, 0, 0, 0, 0, 0, 0, 0, 25, 25, 0, 0, 0, 0, 0, 0, 0, 0, 0, 0, 0, 25, 25, 0, 0, 0, 0, 0, 0, 0, 0, 0, 25, 0, 0, 0, 0, 25, 0, 0, 0, 0, 25, 0, 0, 0, 0, 0, 0, 0, 0, 0, 0, 0, 25, 0, 0, 0, 0, 25, 0, 0, 0, 0, 4, 5, 6, 0, 0, 0, 25, 0, 0, 0, 0, 0, 0, 0, 0, 0, 0, 0, 0, 0, 0, 0, 0, 0, 0, 0, 0, 0, 0, 0, 25, 25, 25, 25, 25, 0, 0, 0, 0, 0, 0, 0, 0, 0, 0, 0, 0, 25, 25, 25, 25, 25, 0, 0, 0, 0, 0, 0, 0, 0, 0, 0, 0, 0, 0, 0, 0, 0, 0, 0, 0, 0, 0, 0, 27, 27, 27, 27, 17, 17, 17, 17, 17, 17, 0, 0, 0, 0, 0, 0, 0, 0, 0, 0, 0, 0, 0, 0, 0, 0, 0, 0, 0, 0, 0, 0, 0, 0, 0, 0, 25, 0, 0, 0, 0, 25, 0, 0, 4, 5, 6, 0, 0, 0, 0, 25, 0, 0, 0, 0, 0, 0, 0, 0, 0, 0, 0, 0, 0, 0, 0, 0, 0, 0, 0, 0, 0, 0, 0, 0, 0, 0, 0, 0, 0, 0, 0, 25, 25, 0, 0, 0, 0, 0, 0, 25, 0, 0, 0, 25, 0, 0, 0, 0, 0, 0, 0, 0, 0, 0, 0, 0, 0, 0, 0, 0, 0, 0, 0, 0, 0, 33, 34, 33,
            0, 0, 0, 0, 0, 0, 0, 0, 0, 0, 25, 25, 0, 0, 0, 0, 25, 0, 0, 0, 25, 0, 0, 0, 0, 0, 0, 25, 0, 0, 0, 0, 0, 0, 25, 0, 0, 0, 0, 0, 0, 0, 0, 0, 0, 0, 0, 0, 0, 0, 25, 25, 0, 0, 0, 0, 0, 0, 0, 0, 0, 0, 0, 25, 25, 0, 0, 0, 0, 0, 0, 0, 0, 0, 25, 0, 0, 0, 0, 25, 0, 0, 0, 0, 25, 0, 0, 0, 4, 5, 5, 5, 5, 6, 0, 0, 25, 0, 0, 0, 0, 25, 0, 0, 0, 0, 0, 25, 0, 0, 0, 0, 25, 0, 0, 0, 0, 0, 0, 0, 0, 0, 0, 0, 0, 0, 0, 0, 0, 0, 0, 0, 0, 0, 0, 0, 25, 25, 25, 25, 25, 0, 0, 0, 0, 0, 0, 0, 0, 0, 0, 0, 0, 25, 25, 25, 25, 25, 0, 0, 0, 0, 0, 0, 0, 0, 0, 0, 0, 0, 0, 0, 0, 0, 0, 0, 0, 0, 0, 17, 17, 17, 17, 17, 17, 17, 17, 17, 17, 17, 0, 0, 0, 0, 0, 0, 0, 0, 0, 0, 0, 0, 0, 0, 0, 0, 0, 0, 0, 4, 5, 6, 0, 0, 0, 0, 25, 0, 0, 0, 0, 25, 0, 0, 0, 25, 0, 0, 0, 0, 0, 25, 0, 0, 0, 0, 0, 0, 0, 0, 0, 0, 0, 0, 0, 0, 0, 0, 0, 0, 0, 0, 0, 0, 0, 0, 0, 0, 0, 0, 0, 0, 0, 25, 25, 0, 0, 0, 0, 0, 0, 25, 0, 0, 0, 25, 0, 0, 0, 0, 0, 0, 0, 0, 0, 0, 0, 0, 0, 0, 0, 0, 0, 0, 0, 0, 0, 49, 50, 33,
            85, 85, 85, 85, 85, 85, 0, 0, 0, 0, 25, 25, 0, 0, 0, 0, 25, 0, 0, 0, 25, 0, 0, 0, 0, 0, 0, 25, 0, 0, 0, 0, 0, 0, 25, 0, 0, 0, 0, 0, 0, 0, 0, 0, 0, 0, 0, 0, 0, 0, 25, 25, 0, 0, 0, 0, 0, 0, 0, 0, 0, 0, 0, 25, 25, 0, 0, 0, 0, 0, 0, 0, 0, 0, 25, 0, 0, 0, 0, 25, 0, 0, 0, 0, 25, 0, 0, 0, 0, 0, 25, 25, 0, 0, 0, 0, 25, 0, 0, 0, 0, 25, 0, 0, 0, 0, 0, 25, 0, 0, 0, 0, 25, 0, 0, 0, 0, 0, 0, 0, 0, 0, 0, 0, 0, 0, 0, 0, 0, 0, 0, 0, 0, 0, 0, 0, 25, 25, 25, 25, 25, 0, 0, 0, 0, 0, 0, 0, 0, 0, 0, 0, 0, 25, 25, 25, 25, 25, 0, 0, 0, 0, 0, 0, 0, 0, 0, 0, 0, 0, 4, 5, 6, 0, 0, 0, 0, 0, 17, 17, 17, 17, 17, 17, 17, 17, 17, 17, 17, 17, 0, 0, 0, 0, 0, 0, 0, 0, 0, 0, 0, 0, 0, 0, 0, 0, 0, 0, 0, 0, 25, 0, 0, 0, 0, 0, 25, 0, 0, 0, 0, 25, 0, 0, 0, 25, 0, 0, 0, 0, 0, 25, 0, 0, 0, 0, 0, 0, 0, 0, 0, 0, 0, 0, 0, 0, 0, 0, 0, 0, 0, 0, 0, 85, 85, 85, 85, 85, 85, 0, 0, 0, 0, 25, 25, 0, 0, 0, 0, 0, 0, 25, 0, 0, 0, 25, 0, 0, 0, 0, 0, 0, 0, 0, 0, 0, 0, 0, 0, 0, 0, 0, 0, 0, 0, 0, 0, 65, 66, 33,
            117, 117, 117, 117, 117, 117, 0, 0, 0, 0, 25, 25, 0, 0, 0, 0, 25, 0, 0, 0, 25, 0, 0, 0, 0, 0, 0, 25, 0, 0, 0, 0, 0, 0, 25, 0, 0, 0, 0, 0, 0, 0, 0, 0, 0, 0, 0, 0, 0, 0, 25, 25, 0, 0, 0, 0, 0, 0, 0, 0, 0, 0, 0, 25, 25, 0, 0, 0, 0, 0, 0, 0, 0, 0, 25, 0, 0, 0, 0, 25, 0, 0, 0, 0, 25, 0, 0, 0, 0, 0, 25, 25, 0, 0, 0, 0, 25, 0, 0, 0, 0, 25, 0, 0, 0, 0, 0, 25, 0, 0, 0, 0, 25, 0, 0, 0, 0, 0, 0, 0, 0, 0, 0, 0, 0, 0, 0, 0, 0, 0, 0, 0, 0, 0, 0, 0, 25, 25, 25, 25, 25, 0, 0, 0, 0, 0, 0, 0, 0, 0, 0, 0, 0, 25, 25, 25, 25, 25, 0, 0, 0, 0, 0, 0, 0, 0, 0, 0, 0, 0, 0, 25, 0, 0, 0, 0, 0, 17, 17, 17, 17, 17, 17, 17, 17, 17, 17, 17, 17, 17, 0, 0, 0, 0, 0, 0, 0, 0, 0, 0, 0, 0, 0, 0, 0, 0, 0, 0, 0, 0, 25, 0, 0, 0, 0, 0, 25, 0, 0, 0, 0, 25, 0, 0, 0, 25, 0, 0, 0, 0, 0, 25, 0, 0, 0, 0, 0, 0, 0, 0, 0, 0, 0, 0, 0, 0, 0, 0, 0, 0, 0, 0, 0, 117, 117, 117, 117, 117, 117, 0, 0, 0, 0, 25, 25, 0, 0, 0, 0, 0, 0, 25, 0, 0, 0, 25, 0, 0, 0, 0, 33, 34, 33, 34, 33, 34, 33, 34, 33, 34, 33, 34, 33, 34, 33, 34, 33, 34, 33, 34],
         "height":18,
         "id":1,
         "name":"foregroundLayer",
         "opacity":1,
         "type":"tilelayer",
         "visible":true,
         "width":300,
         "x":0,
         "y":0
        }, 
        {
         "data":[0, 0, 0, 0, 0, 0, 0, 0, 0, 0, 0, 0, 0, 0, 0, 0, 0, 0, 0, 0, 0, 0, 0, 0, 0, 0, 0, 0, 0, 0, 0, 0, 0, 0, 0, 0, 0, 0, 0, 0, 0, 0, 0, 0, 0, 0, 0, 0, 0, 0, 0, 0, 0, 0, 0, 0, 0, 0, 0, 0, 0, 0, 0, 0, 0, 0, 0, 0, 0, 0, 0, 0, 0, 0, 0, 0, 0, 0, 0, 0, 0, 0, 0, 0, 0, 0, 0, 0, 0, 0, 0, 0, 0, 0, 0, 0, 0, 0, 0, 0, 0, 0, 0, 0, 0, 0, 0, 0, 0, 0, 0, 0, 0, 0, 0, 0, 0, 0, 0, 0, 0, 0, 0, 0, 0, 0, 0, 0, 0, 0, 0, 0, 0, 0, 0, 0, 0, 0, 0, 0, 0, 0, 0, 0, 0, 0, 0, 0, 0, 0, 182, 183, 184, 185, 0, 0, 0, 0, 0, 0, 0, 0, 0, 0, 0, 0, 0, 0, 0, 0, 0, 0, 0, 0, 0, 0, 0, 0, 0, 0, 0, 0, 0, 0, 0, 0, 0, 0, 0, 0, 0, 0, 0, 0, 0, 0, 0, 0, 0, 0, 0, 0, 0, 0, 0, 0, 0, 0, 0, 0, 0, 0, 0, 0, 0, 0, 0, 0, 0, 0, 0, 0, 0, 0, 0, 0, 0, 0, 0, 0, 0, 0, 0, 0, 0, 0, 0, 0, 0, 0, 0, 0, 0, 0, 0, 0, 0, 0, 0, 0, 0, 0, 0, 0, 0, 0, 0, 0, 0, 0, 0, 0, 0, 0, 0, 0, 0, 0, 0, 0, 0, 0, 0, 0, 0, 0, 0, 0, 0, 0, 0, 0, 0, 0, 0, 0, 0, 0, 0, 0, 0, 0, 0, 0, 0, 0, 0, 0, 0, 0,
            0, 0, 0, 0, 0, 0, 0, 0, 0, 0, 0, 0, 0, 0, 0, 0, 0, 0, 0, 0, 0, 0, 0, 0, 0, 0, 0, 0, 0, 0, 0, 0, 0, 0, 0, 0, 0, 0, 0, 0, 0, 0, 0, 0, 0, 0, 0, 0, 0, 0, 0, 0, 0, 0, 0, 0, 0, 0, 0, 0, 0, 0, 0, 0, 0, 0, 0, 0, 0, 0, 0, 0, 0, 0, 0, 0, 0, 0, 0, 0, 0, 0, 0, 0, 0, 0, 0, 0, 0, 0, 0, 0, 0, 0, 0, 0, 0, 0, 0, 0, 0, 0, 0, 0, 0, 0, 0, 0, 0, 0, 0, 0, 0, 0, 0, 0, 0, 0, 0, 0, 0, 0, 0, 0, 0, 0, 0, 0, 0, 0, 0, 0, 0, 0, 0, 0, 0, 0, 0, 0, 0, 0, 0, 0, 0, 0, 0, 0, 0, 0, 198, 199, 200, 201, 0, 0, 0, 0, 0, 0, 0, 0, 0, 0, 0, 0, 0, 0, 0, 0, 0, 0, 0, 0, 0, 0, 0, 0, 0, 0, 0, 0, 0, 0, 0, 0, 0, 0, 0, 0, 0, 0, 0, 0, 0, 0, 0, 0, 0, 0, 0, 0, 0, 0, 0, 0, 0, 0, 0, 0, 0, 0, 0, 0, 0, 0, 0, 0, 0, 0, 0, 0, 0, 0, 0, 0, 0, 0, 0, 0, 0, 0, 0, 0, 0, 0, 0, 0, 0, 0, 0, 0, 0, 0, 0, 0, 0, 0, 0, 0, 0, 0, 0, 0, 0, 0, 0, 0, 0, 0, 0, 0, 0, 0, 0, 0, 0, 0, 0, 0, 0, 0, 0, 0, 0, 0, 0, 0, 0, 0, 0, 0, 0, 0, 0, 0, 0, 0, 0, 0, 0, 0, 0, 0, 0, 0, 0, 0, 0, 0,
            89, 89, 89, 89, 89, 89, 89, 89, 89, 89, 89, 89, 89, 89, 89, 89, 89, 89, 89, 89, 89, 89, 89, 89, 89, 89, 89, 89, 89, 89, 89, 89, 89, 89, 89, 89, 89, 89, 89, 89, 89, 89, 89, 89, 89, 89, 89, 89, 89, 89, 89, 89, 89, 89, 89, 89, 89, 89, 89, 89, 89, 89, 89, 89, 89, 89, 89, 89, 89, 89, 89, 89, 89, 89, 89, 89, 89, 89, 89, 89, 89, 89, 89, 89, 89, 89, 89, 89, 89, 89, 89, 89, 89, 89, 89, 89, 89, 89, 89, 89, 89, 89, 89, 89, 89, 89, 89, 89, 89, 89, 89, 89, 89, 89, 89, 89, 89, 89, 89, 89, 89, 89, 89, 89, 89, 89, 89, 89, 89, 89, 89, 89, 89, 89, 89, 89, 89, 89, 89, 89, 89, 89, 89, 89, 89, 89, 89, 89, 89, 89, 214, 215, 216, 217, 89, 89, 89, 89, 89, 89, 89, 89, 89, 89, 89, 89, 89, 89, 89, 89, 89, 89, 89, 89, 89, 89, 89, 89, 89, 89, 89, 89, 89, 89, 89, 89, 89, 89, 89, 89, 89, 89, 89, 89, 89, 89, 89, 89, 89, 89, 89, 89, 89, 89, 89, 89, 89, 89, 89, 89, 89, 89, 89, 89, 89, 89, 89, 89, 89, 89, 89, 89, 89, 89, 89, 89, 89, 89, 89, 89, 89, 89, 89, 89, 89, 89, 89, 89, 89, 89, 89, 89, 89, 89, 89, 89, 89, 89, 89, 89, 89, 89, 89, 89, 89, 89, 89, 89, 89, 89, 89, 89, 89, 89, 89, 89, 89, 89, 89, 89, 89, 89, 89, 89, 89, 89, 89, 89, 89, 89, 0, 0, 0, 0, 0, 0, 0, 0, 0, 0, 0, 0, 0, 0, 0, 0, 0, 0, 0, 0,
            105, 105, 105, 105, 105, 105, 105, 105, 105, 105, 105, 105, 105, 105, 105, 105, 105, 105, 105, 105, 105, 105, 105, 105, 105, 105, 105, 105, 105, 105, 105, 105, 105, 105, 105, 105, 105, 105, 105, 105, 105, 105, 105, 105, 105, 105, 105, 105, 105, 105, 105, 105, 105, 105, 105, 105, 105, 105, 105, 105, 105, 105, 105, 105, 105, 105, 105, 105, 105, 105, 105, 105, 105, 105, 105, 105, 105, 105, 105, 105, 105, 105, 105, 105, 105, 105, 105, 105, 105, 105, 105, 105, 105, 105, 105, 105, 105, 105, 105, 105, 105, 105, 105, 105, 105, 105, 105, 105, 105, 105, 105, 105, 105, 105, 105, 105, 105, 105, 105, 105, 105, 105, 105, 105, 105, 105, 105, 105, 105, 105, 105, 105, 105, 105, 105, 105, 105, 105, 105, 105, 105, 105, 105, 105, 105, 105, 105, 105, 105, 105, 105, 105, 105, 105, 105, 105, 105, 105, 105, 105, 105, 105, 105, 105, 105, 105, 105, 105, 105, 105, 105, 105, 105, 105, 105, 105, 105, 105, 105, 105, 105, 105, 105, 105, 105, 105, 105, 105, 105, 105, 105, 105, 105, 105, 105, 105, 105, 105, 105, 105, 105, 105, 105, 105, 105, 105, 105, 105, 105, 105, 105, 105, 105, 105, 105, 105, 105, 105, 105, 105, 105, 105, 105, 105, 105, 105, 105, 105, 105, 105, 105, 105, 105, 105, 105, 105, 105, 105, 105, 105, 105, 105, 105, 105, 105, 105, 105, 105, 105, 105, 105, 105, 105, 105, 105, 105, 105, 105, 105, 105, 105, 105, 105, 105, 105, 105, 105, 105, 105, 105, 105, 105, 105, 105, 105, 105, 105, 105, 105, 105, 0, 0, 0, 0, 0, 0, 0, 0, 0, 0, 0, 0, 0, 0, 0, 0, 0, 0, 0, 0,
            0, 0, 0, 0, 0, 0, 0, 285, 286, 287, 285, 286, 287, 288, 0, 0, 0, 0, 0, 0, 0, 0, 0, 0, 0, 0, 0, 0, 0, 0, 0, 253, 254, 255, 254, 255, 256, 0, 0, 0, 253, 0, 0, 0, 0, 0, 0, 0, 0, 0, 0, 0, 0, 0, 0, 0, 0, 0, 0, 0, 0, 0, 0, 0, 0, 0, 0, 0, 0, 0, 0, 0, 0, 0, 0, 0, 0, 0, 0, 0, 253, 0, 0, 0, 0, 0, 0, 0, 0, 253, 254, 255, 254, 255, 256, 0, 0, 0, 0, 0, 0, 0, 0, 0, 0, 0, 0, 0, 0, 0, 0, 0, 0, 0, 0, 0, 0, 0, 0, 0, 253, 254, 255, 254, 255, 256, 0, 0, 0, 0, 0, 0, 0, 0, 0, 0, 0, 0, 0, 0, 0, 0, 0, 0, 0, 0, 0, 0, 0, 0, 0, 0, 0, 0, 0, 0, 0, 0, 0, 0, 0, 0, 0, 0, 0, 0, 0, 0, 0, 0, 0, 0, 0, 0, 0, 0, 0, 0, 0, 0, 0, 0, 0, 0, 0, 0, 0, 0, 0, 0, 0, 0, 0, 0, 0, 0, 0, 0, 253, 254, 255, 256, 0, 0, 0, 0, 0, 0, 285, 286, 287, 288, 0, 0, 0, 0, 0, 0, 0, 0, 0, 0, 0, 0, 0, 0, 0, 0, 0, 0, 0, 0, 0, 0, 0, 0, 0, 0, 0, 0, 0, 0, 0, 0, 0, 0, 0, 0, 0, 0, 0, 0, 0, 0, 0, 0, 0, 0, 0, 0, 0, 0, 0, 0, 0, 0, 0, 0, 0, 0, 0, 0, 0, 0, 0, 0, 0, 0, 0, 0, 0, 0, 0, 0, 0, 0, 0, 0, 0, 0, 0, 0, 0, 0, 0, 0, 0, 0, 0, 0,
            0, 0, 0, 0, 0, 0, 0, 301, 302, 303, 301, 302, 303, 304, 0, 0, 0, 0, 0, 0, 0, 0, 0, 0, 0, 0, 0, 0, 0, 0, 0, 269, 270, 271, 270, 271, 272, 0, 0, 0, 0, 0, 0, 0, 0, 0, 0, 0, 0, 0, 0, 0, 0, 0, 0, 0, 0, 0, 0, 0, 0, 0, 0, 0, 0, 0, 0, 0, 0, 0, 0, 0, 0, 0, 0, 0, 0, 0, 0, 0, 0, 0, 0, 0, 0, 0, 0, 0, 0, 269, 270, 271, 270, 271, 272, 0, 0, 0, 0, 0, 0, 0, 0, 0, 0, 0, 0, 0, 0, 0, 0, 0, 0, 0, 0, 0, 0, 0, 0, 0, 269, 270, 271, 270, 271, 272, 0, 0, 0, 0, 0, 0, 0, 0, 0, 0, 0, 0, 0, 0, 0, 0, 0, 0, 0, 0, 0, 0, 0, 0, 0, 0, 0, 0, 0, 0, 0, 0, 0, 0, 0, 0, 0, 0, 0, 0, 0, 0, 0, 0, 0, 253, 254, 255, 256, 0, 0, 0, 0, 0, 0, 0, 0, 0, 0, 0, 0, 0, 0, 0, 0, 0, 0, 0, 0, 0, 0, 0, 269, 270, 271, 272, 0, 0, 0, 0, 0, 0, 301, 302, 303, 304, 0, 0, 0, 0, 0, 0, 0, 0, 0, 0, 0, 0, 0, 0, 0, 0, 0, 0, 0, 0, 0, 0, 0, 0, 0, 0, 0, 0, 0, 0, 0, 0, 0, 0, 0, 0, 0, 0, 0, 0, 0, 0, 0, 0, 0, 0, 0, 0, 0, 0, 0, 0, 0, 0, 0, 0, 0, 0, 0, 0, 0, 0, 0, 0, 0, 0, 0, 0, 0, 0, 0, 0, 0, 0, 0, 0, 0, 0, 0, 0, 0, 0, 0, 0, 0, 0, 0, 0,
            0, 0, 0, 0, 0, 0, 0, 0, 0, 0, 0, 0, 0, 0, 0, 0, 0, 0, 0, 0, 0, 0, 0, 0, 0, 0, 0, 0, 0, 0, 0, 0, 0, 0, 0, 0, 0, 0, 0, 0, 0, 0, 0, 0, 0, 0, 0, 0, 0, 0, 0, 0, 0, 0, 0, 0, 0, 0, 0, 0, 0, 0, 0, 0, 0, 0, 0, 0, 0, 0, 0, 0, 0, 0, 0, 0, 0, 0, 0, 0, 0, 0, 0, 0, 0, 0, 0, 0, 0, 0, 0, 0, 0, 0, 0, 0, 0, 0, 0, 0, 0, 0, 0, 0, 0, 0, 0, 0, 0, 0, 0, 0, 0, 0, 0, 0, 0, 0, 0, 0, 0, 0, 0, 0, 0, 0, 0, 0, 0, 0, 0, 0, 0, 0, 0, 0, 0, 0, 0, 0, 0, 0, 0, 0, 0, 0, 0, 0, 0, 0, 0, 0, 0, 0, 0, 0, 0, 0, 0, 0, 0, 0, 0, 0, 0, 0, 0, 0, 0, 0, 0, 269, 270, 271, 272, 0, 0, 0, 0, 0, 0, 0, 0, 0, 0, 0, 0, 0, 0, 0, 0, 0, 0, 0, 0, 0, 0, 0, 0, 0, 0, 0, 0, 0, 0, 0, 0, 0, 0, 0, 0, 0, 0, 0, 0, 0, 0, 0, 0, 0, 0, 0, 0, 0, 0, 0, 0, 0, 0, 0, 0, 0, 0, 0, 0, 0, 0, 0, 0, 0, 0, 0, 0, 0, 0, 0, 0, 0, 0, 0, 0, 0, 0, 0, 0, 0, 0, 0, 0, 0, 0, 0, 0, 0, 0, 0, 0, 0, 0, 0, 0, 0, 0, 0, 0, 0, 0, 0, 0, 0, 0, 0, 0, 0, 0, 0, 0, 0, 0, 0, 0, 0, 0, 0, 0, 0, 0, 0, 0, 0,
            0, 0, 0, 0, 0, 0, 0, 0, 0, 0, 0, 0, 0, 0, 0, 0, 0, 0, 0, 0, 0, 0, 0, 0, 0, 0, 0, 0, 0, 0, 0, 0, 0, 0, 0, 0, 0, 0, 0, 0, 0, 0, 0, 0, 0, 0, 0, 0, 0, 0, 0, 0, 0, 0, 0, 0, 0, 0, 0, 0, 0, 0, 0, 0, 0, 0, 0, 0, 0, 0, 0, 0, 0, 0, 0, 0, 0, 0, 0, 0, 0, 0, 0, 0, 0, 0, 0, 0, 0, 0, 0, 0, 0, 0, 0, 0, 0, 0, 0, 0, 0, 0, 0, 0, 0, 0, 0, 0, 0, 0, 0, 0, 0, 0, 0, 0, 0, 0, 0, 0, 0, 0, 0, 0, 0, 0, 0, 0, 0, 0, 0, 0, 0, 0, 0, 0, 0, 0, 0, 0, 0, 0, 0, 0, 0, 0, 0, 0, 0, 0, 0, 0, 0, 0, 0, 0, 0, 0, 0, 0, 0, 0, 0, 0, 0, 0, 0, 0, 0, 0, 0, 0, 0, 0, 0, 0, 0, 0, 0, 0, 0, 0, 0, 0, 0, 0, 0, 0, 0, 0, 0, 0, 0, 0, 0, 0, 0, 0, 0, 0, 0, 0, 0, 0, 0, 0, 0, 0, 0, 0, 0, 0, 0, 0, 0, 0, 0, 0, 0, 0, 0, 0, 0, 0, 0, 0, 0, 0, 0, 0, 0, 0, 0, 0, 0, 0, 0, 0, 0, 0, 0, 0, 0, 0, 0, 0, 0, 0, 0, 0, 0, 0, 0, 0, 0, 0, 0, 0, 0, 0, 0, 0, 0, 0, 0, 0, 0, 0, 0, 0, 0, 0, 0, 0, 0, 0, 0, 0, 0, 0, 0, 0, 0, 0, 0, 0, 0, 0, 0, 0, 0, 0, 0, 0, 0, 0, 0, 0, 0, 0,
            0, 0, 0, 0, 0, 0, 0, 0, 0, 0, 0, 0, 0, 0, 0, 0, 0, 0, 0, 0, 0, 0, 0, 0, 0, 0, 0, 0, 0, 0, 0, 0, 0, 0, 0, 0, 0, 0, 0, 0, 0, 0, 0, 0, 0, 0, 0, 0, 0, 0, 0, 0, 0, 0, 0, 0, 0, 0, 0, 0, 0, 0, 0, 0, 0, 0, 0, 0, 0, 0, 0, 0, 0, 0, 0, 0, 0, 0, 0, 0, 0, 0, 0, 0, 0, 0, 0, 0, 0, 0, 0, 0, 0, 0, 0, 0, 0, 0, 0, 0, 0, 0, 0, 0, 0, 0, 0, 0, 0, 0, 0, 0, 0, 0, 0, 0, 0, 0, 0, 0, 0, 0, 0, 0, 0, 0, 0, 0, 0, 0, 0, 0, 0, 0, 0, 0, 0, 0, 0, 0, 0, 0, 0, 0, 0, 0, 0, 0, 0, 0, 0, 0, 0, 0, 0, 0, 0, 0, 0, 0, 0, 0, 0, 0, 0, 0, 0, 0, 0, 0, 0, 0, 0, 0, 0, 0, 0, 0, 0, 0, 0, 0, 0, 0, 0, 0, 0, 0, 0, 0, 0, 0, 0, 0, 0, 0, 0, 0, 0, 0, 0, 0, 0, 0, 0, 0, 0, 0, 0, 0, 0, 0, 0, 0, 0, 0, 0, 0, 0, 0, 0, 0, 0, 0, 0, 0, 0, 0, 0, 0, 0, 0, 0, 0, 0, 0, 0, 0, 0, 0, 0, 0, 0, 0, 0, 0, 0, 0, 0, 0, 0, 0, 0, 0, 0, 0, 0, 0, 0, 0, 0, 0, 0, 0, 0, 0, 0, 0, 0, 0, 0, 0, 0, 0, 0, 0, 0, 0, 0, 0, 0, 0, 0, 0, 0, 0, 0, 0, 0, 0, 0, 0, 0, 0, 0, 0, 0, 0, 0, 0,
            0, 0, 0, 0, 0, 0, 0, 0, 0, 0, 0, 0, 0, 0, 0, 0, 0, 0, 0, 0, 0, 0, 0, 0, 0, 0, 0, 0, 0, 0, 0, 0, 0, 0, 0, 0, 0, 0, 0, 0, 0, 0, 0, 0, 0, 0, 0, 0, 0, 0, 0, 0, 0, 0, 0, 0, 0, 0, 0, 0, 0, 0, 0, 0, 0, 0, 0, 0, 0, 0, 0, 0, 0, 0, 0, 0, 0, 0, 0, 0, 0, 0, 0, 0, 0, 0, 0, 0, 0, 0, 0, 0, 0, 0, 0, 0, 0, 0, 0, 0, 0, 0, 0, 0, 0, 0, 0, 0, 0, 0, 0, 0, 0, 0, 0, 0, 0, 0, 0, 0, 0, 0, 0, 0, 0, 0, 0, 0, 0, 0, 0, 0, 0, 0, 0, 0, 0, 0, 0, 0, 0, 0, 0, 0, 0, 0, 0, 0, 0, 0, 0, 0, 0, 0, 0, 0, 0, 0, 0, 0, 0, 0, 0, 0, 0, 0, 0, 0, 0, 0, 0, 0, 0, 0, 0, 0, 0, 0, 0, 0, 0, 0, 0, 0, 0, 0, 0, 0, 0, 0, 0, 0, 0, 0, 0, 0, 0, 0, 0, 162, 163, 0, 0, 0, 0, 0, 0, 0, 0, 0, 0, 0, 0, 0, 0, 0, 0, 0, 0, 0, 0, 0, 0, 0, 0, 0, 0, 0, 0, 0, 0, 0, 0, 0, 0, 0, 0, 0, 0, 0, 0, 0, 0, 0, 0, 0, 0, 0, 0, 0, 0, 0, 0, 0, 0, 0, 0, 0, 0, 0, 0, 0, 0, 0, 0, 0, 0, 0, 0, 0, 0, 0, 0, 0, 0, 0, 0, 0, 0, 0, 0, 0, 0, 0, 0, 0, 0, 0, 0, 0, 0, 0, 0, 0, 0, 0, 0, 0, 0, 0,
            0, 0, 0, 0, 0, 0, 0, 0, 0, 0, 0, 0, 0, 0, 0, 0, 0, 0, 0, 0, 0, 0, 0, 0, 0, 0, 0, 0, 0, 0, 0, 0, 0, 0, 0, 0, 0, 0, 0, 0, 0, 0, 0, 0, 0, 0, 0, 0, 0, 0, 0, 0, 0, 0, 0, 0, 0, 0, 0, 0, 0, 0, 0, 0, 0, 0, 0, 0, 0, 0, 0, 0, 0, 0, 0, 0, 0, 0, 0, 0, 0, 0, 0, 0, 0, 0, 0, 0, 0, 0, 0, 0, 0, 0, 0, 0, 0, 0, 0, 0, 0, 0, 0, 0, 0, 0, 0, 0, 0, 0, 0, 0, 0, 0, 0, 0, 0, 0, 0, 0, 0, 0, 0, 0, 0, 0, 0, 0, 0, 0, 0, 0, 0, 0, 0, 0, 0, 0, 0, 0, 0, 0, 0, 0, 0, 0, 0, 0, 0, 0, 0, 0, 0, 0, 0, 0, 0, 0, 0, 0, 0, 0, 0, 0, 0, 0, 0, 0, 0, 0, 0, 0, 0, 0, 0, 0, 0, 0, 0, 0, 0, 0, 0, 0, 0, 0, 0, 0, 0, 0, 0, 0, 0, 0, 0, 0, 0, 0, 162, 0, 0, 163, 0, 0, 0, 0, 0, 0, 0, 0, 0, 0, 0, 0, 0, 0, 0, 0, 0, 0, 0, 0, 0, 0, 0, 0, 0, 0, 0, 0, 0, 0, 0, 0, 0, 0, 0, 0, 0, 0, 0, 0, 0, 0, 0, 0, 0, 0, 0, 0, 0, 0, 0, 0, 0, 0, 0, 0, 0, 0, 0, 0, 0, 0, 0, 0, 0, 0, 0, 0, 0, 0, 0, 0, 0, 0, 0, 0, 0, 0, 0, 0, 0, 0, 0, 0, 0, 0, 0, 0, 0, 0, 0, 0, 0, 0, 0, 0, 0, 0,
            0, 0, 0, 0, 0, 0, 0, 0, 0, 0, 0, 0, 0, 0, 0, 0, 0, 0, 0, 0, 0, 0, 0, 0, 0, 0, 0, 0, 0, 0, 162, 163, 0, 0, 0, 0, 0, 0, 0, 0, 0, 0, 0, 0, 0, 0, 0, 0, 0, 0, 0, 0, 0, 0, 0, 0, 0, 0, 0, 0, 0, 0, 0, 0, 0, 0, 0, 0, 0, 0, 0, 0, 0, 0, 0, 0, 0, 0, 0, 0, 0, 0, 0, 0, 0, 0, 0, 0, 0, 0, 0, 0, 0, 0, 0, 0, 0, 0, 0, 0, 0, 0, 0, 0, 0, 0, 0, 0, 0, 0, 0, 0, 0, 0, 0, 0, 0, 0, 0, 0, 0, 0, 0, 0, 0, 0, 0, 0, 0, 0, 0, 0, 0, 0, 0, 0, 0, 0, 0, 0, 0, 0, 0, 0, 0, 0, 0, 0, 0, 0, 0, 0, 0, 0, 0, 0, 0, 0, 0, 0, 0, 0, 0, 0, 0, 0, 0, 0, 0, 0, 0, 0, 0, 0, 0, 0, 0, 0, 0, 0, 0, 0, 0, 0, 0, 0, 0, 0, 0, 0, 0, 0, 0, 0, 0, 0, 0, 162, 0, 0, 0, 0, 163, 0, 0, 0, 0, 0, 0, 0, 0, 0, 0, 0, 0, 0, 0, 0, 0, 0, 0, 0, 0, 0, 0, 0, 0, 0, 0, 0, 0, 0, 0, 0, 0, 0, 0, 0, 0, 0, 0, 0, 0, 0, 0, 0, 162, 163, 0, 0, 0, 0, 0, 0, 0, 0, 0, 0, 0, 0, 0, 0, 0, 0, 0, 0, 0, 0, 0, 0, 0, 0, 0, 0, 0, 0, 0, 0, 0, 0, 0, 0, 0, 0, 0, 0, 0, 0, 0, 0, 0, 0, 0, 0, 0, 0, 0, 0, 0, 0,
            0, 0, 0, 0, 0, 0, 0, 0, 0, 0, 0, 0, 0, 0, 0, 0, 0, 0, 0, 0, 0, 0, 0, 0, 0, 0, 0, 0, 0, 162, 0, 0, 163, 0, 0, 0, 0, 0, 0, 0, 0, 0, 0, 0, 0, 0, 0, 0, 0, 0, 0, 0, 0, 0, 0, 0, 0, 0, 0, 0, 0, 0, 0, 0, 0, 0, 0, 0, 0, 0, 0, 0, 0, 0, 0, 0, 0, 0, 0, 0, 0, 0, 0, 0, 0, 0, 0, 0, 0, 0, 0, 0, 0, 0, 0, 0, 0, 0, 0, 0, 0, 0, 0, 0, 0, 0, 0, 0, 0, 0, 0, 0, 0, 0, 0, 0, 0, 0, 0, 0, 0, 0, 0, 0, 0, 0, 0, 0, 0, 0, 0, 0, 0, 0, 0, 0, 0, 0, 0, 0, 0, 0, 0, 0, 0, 0, 0, 0, 0, 0, 0, 0, 0, 0, 0, 0, 0, 0, 0, 0, 0, 0, 0, 0, 0, 0, 0, 0, 0, 0, 0, 0, 0, 0, 0, 0, 0, 0, 0, 0, 0, 0, 0, 0, 0, 0, 0, 0, 0, 0, 0, 0, 0, 0, 0, 0, 162, 0, 0, 0, 0, 0, 0, 163, 0, 0, 0, 0, 0, 0, 0, 0, 0, 0, 0, 0, 0, 0, 0, 0, 0, 0, 0, 0, 0, 0, 0, 0, 0, 0, 0, 0, 0, 0, 0, 0, 0, 0, 0, 0, 0, 0, 0, 0, 0, 162, 0, 0, 163, 0, 0, 0, 0, 0, 0, 0, 0, 0, 0, 0, 0, 0, 0, 0, 0, 0, 0, 0, 0, 0, 0, 0, 0, 0, 0, 0, 0, 0, 0, 0, 0, 0, 0, 0, 0, 0, 0, 0, 0, 0, 0, 0, 0, 0, 0, 0, 0, 0, 0, 0,
            0, 0, 0, 145, 146, 0, 0, 0, 0, 0, 0, 0, 0, 0, 0, 0, 0, 0, 0, 0, 0, 0, 0, 0, 0, 0, 0, 0, 0, 0, 0, 0, 0, 163, 0, 0, 0, 0, 0, 0, 170, 171, 172, 173, 0, 0, 0, 0, 0, 0, 0, 0, 0, 0, 0, 0, 0, 0, 0, 0, 0, 0, 0, 0, 0, 0, 0, 0, 0, 0, 0, 0, 0, 0, 0, 0, 0, 0, 0, 0, 0, 0, 0, 0, 0, 0, 0, 0, 0, 0, 0, 0, 0, 0, 0, 0, 0, 0, 0, 0, 0, 0, 0, 0, 0, 0, 0, 0, 0, 0, 0, 0, 0, 0, 0, 0, 0, 0, 0, 0, 0, 0, 0, 0, 0, 0, 0, 0, 0, 0, 0, 231, 232, 233, 0, 0, 0, 0, 0, 0, 0, 0, 0, 0, 0, 0, 0, 0, 0, 0, 0, 0, 0, 0, 0, 0, 0, 0, 0, 0, 0, 0, 0, 0, 0, 0, 0, 0, 0, 0, 0, 0, 0, 0, 0, 0, 0, 0, 0, 0, 0, 0, 0, 0, 0, 0, 0, 0, 0, 0, 0, 0, 0, 0, 0, 162, 0, 0, 0, 0, 0, 0, 0, 0, 163, 0, 0, 0, 0, 0, 0, 0, 0, 0, 0, 0, 0, 0, 0, 0, 0, 0, 0, 0, 0, 0, 0, 0, 0, 0, 0, 0, 0, 0, 0, 0, 0, 0, 0, 0, 0, 0, 0, 0, 162, 0, 0, 0, 0, 163, 0, 0, 0, 0, 0, 0, 0, 0, 0, 0, 0, 0, 0, 0, 0, 0, 0, 0, 0, 0, 0, 0, 0, 0, 0, 0, 0, 0, 0, 0, 0, 0, 0, 0, 0, 0, 0, 0, 0, 0, 0, 0, 0, 0, 0, 0, 0, 0, 0, 0,
            0, 145, 146, 161, 0, 0, 0, 0, 0, 0, 0, 0, 0, 0, 0, 0, 0, 0, 0, 0, 0, 0, 0, 0, 0, 0, 0, 0, 0, 0, 0, 0, 0, 0, 0, 0, 0, 0, 0, 0, 186, 187, 188, 189, 190, 191, 192, 0, 0, 0, 0, 0, 0, 0, 0, 0, 0, 0, 0, 0, 0, 0, 0, 0, 0, 0, 0, 0, 0, 0, 0, 0, 0, 0, 0, 0, 0, 0, 0, 0, 0, 0, 0, 0, 0, 0, 0, 0, 0, 0, 0, 0, 0, 0, 0, 0, 0, 0, 0, 0, 0, 0, 0, 0, 0, 0, 0, 0, 0, 0, 0, 0, 0, 0, 0, 0, 0, 0, 0, 0, 0, 0, 0, 0, 0, 0, 0, 0, 0, 244, 245, 247, 248, 249, 0, 0, 0, 0, 0, 0, 0, 0, 0, 0, 0, 0, 243, 244, 245, 0, 0, 0, 0, 0, 0, 0, 0, 0, 0, 0, 0, 0, 0, 0, 0, 0, 0, 0, 0, 0, 0, 0, 0, 0, 0, 0, 0, 0, 0, 0, 0, 0, 0, 0, 0, 0, 0, 0, 0, 0, 0, 0, 0, 0, 162, 0, 0, 0, 0, 0, 0, 0, 0, 0, 0, 163, 0, 0, 0, 0, 0, 0, 0, 0, 0, 0, 0, 0, 0, 0, 0, 0, 0, 0, 0, 0, 0, 0, 0, 0, 0, 0, 0, 0, 0, 0, 0, 0, 0, 0, 0, 0, 0, 162, 0, 0, 0, 0, 0, 0, 163, 0, 0, 0, 0, 0, 0, 0, 0, 0, 0, 0, 0, 0, 0, 0, 0, 0, 0, 0, 0, 0, 0, 0, 0, 0, 0, 0, 0, 0, 0, 0, 0, 0, 0, 0, 0, 0, 0, 0, 0, 0, 0, 0, 0, 0, 0, 0, 0, 0,
            0, 161, 0, 161, 0, 0, 0, 0, 0, 0, 0, 0, 0, 0, 0, 0, 0, 0, 0, 0, 0, 0, 0, 0, 162, 163, 162, 0, 0, 0, 0, 145, 146, 0, 0, 163, 0, 0, 0, 0, 202, 203, 204, 205, 206, 207, 208, 0, 0, 0, 0, 0, 0, 0, 0, 0, 0, 0, 0, 0, 0, 0, 0, 0, 0, 0, 0, 0, 257, 258, 259, 0, 0, 0, 0, 0, 0, 0, 0, 0, 0, 0, 0, 0, 0, 0, 0, 0, 0, 0, 0, 0, 0, 0, 0, 0, 0, 0, 0, 0, 0, 0, 0, 0, 0, 0, 0, 0, 0, 0, 0, 0, 0, 0, 0, 0, 145, 146, 0, 0, 0, 0, 0, 0, 0, 0, 0, 0, 0, 260, 261, 263, 264, 265, 0, 0, 0, 0, 0, 0, 0, 0, 0, 0, 0, 0, 0, 260, 261, 0, 0, 0, 0, 0, 0, 0, 0, 0, 0, 0, 0, 0, 0, 0, 0, 0, 145, 146, 0, 0, 0, 0, 0, 0, 0, 0, 0, 0, 0, 0, 0, 0, 0, 0, 0, 0, 0, 0, 0, 0, 0, 0, 0, 162, 0, 0, 0, 0, 0, 0, 0, 0, 0, 0, 0, 0, 163, 145, 146, 0, 0, 0, 0, 0, 0, 0, 0, 0, 0, 0, 0, 0, 0, 0, 0, 0, 0, 0, 0, 0, 0, 0, 0, 0, 0, 0, 0, 0, 0, 0, 162, 163, 162, 0, 0, 0, 0, 145, 146, 0, 0, 163, 0, 0, 0, 0, 0, 0, 0, 0, 0, 0, 0, 0, 0, 0, 0, 0, 145, 146, 0, 0, 0, 0, 0, 0, 0, 0, 0, 0, 0, 0, 0, 0, 0, 0, 0, 0, 0, 0, 0, 0, 0, 0, 0, 0, 0, 0, 0, 0,
            0, 0, 0, 0, 0, 0, 0, 0, 0, 0, 0, 0, 0, 0, 0, 0, 0, 0, 0, 0, 0, 0, 0, 162, 0, 0, 163, 0, 0, 145, 146, 161, 0, 0, 0, 0, 163, 0, 0, 0, 218, 219, 220, 221, 222, 223, 224, 0, 0, 0, 0, 0, 0, 0, 0, 0, 0, 0, 0, 0, 0, 0, 0, 0, 0, 0, 0, 0, 0, 274, 0, 0, 0, 0, 0, 0, 0, 0, 0, 0, 0, 0, 0, 0, 0, 0, 0, 0, 0, 0, 0, 0, 0, 0, 0, 0, 0, 0, 0, 0, 0, 0, 0, 0, 0, 0, 0, 0, 0, 0, 0, 0, 0, 0, 145, 146, 161, 0, 0, 0, 0, 0, 0, 0, 0, 0, 0, 0, 275, 276, 277, 279, 280, 281, 0, 0, 0, 0, 0, 0, 0, 0, 0, 0, 273, 0, 275, 276, 277, 0, 273, 0, 0, 0, 0, 0, 0, 0, 0, 0, 0, 0, 0, 0, 145, 146, 161, 148, 149, 0, 0, 0, 0, 0, 0, 0, 0, 0, 0, 0, 0, 0, 0, 0, 0, 0, 0, 0, 0, 0, 0, 0, 162, 0, 0, 0, 0, 0, 0, 0, 0, 0, 0, 0, 0, 145, 146, 150, 0, 0, 0, 0, 0, 0, 0, 0, 0, 0, 0, 0, 0, 0, 0, 0, 0, 0, 0, 0, 0, 0, 0, 0, 0, 0, 0, 0, 0, 0, 0, 162, 0, 0, 163, 0, 0, 145, 146, 161, 0, 0, 0, 0, 163, 0, 0, 0, 0, 0, 0, 0, 0, 0, 0, 0, 0, 0, 0, 0, 161, 0, 0, 0, 0, 0, 0, 0, 0, 0, 0, 0, 0, 0, 0, 0, 0, 0, 0, 0, 0, 0, 0, 0, 0, 0, 0, 0, 0, 0, 0, 0,
            0, 0, 0, 0, 0, 0, 0, 0, 0, 0, 0, 0, 0, 0, 0, 0, 0, 0, 0, 0, 0, 0, 162, 0, 0, 0, 0, 0, 0, 161, 0, 161, 0, 0, 0, 0, 0, 163, 0, 0, 234, 235, 236, 237, 238, 239, 240, 0, 0, 0, 0, 0, 0, 0, 0, 0, 0, 0, 0, 0, 0, 0, 0, 0, 0, 0, 0, 0, 0, 290, 0, 0, 0, 0, 0, 0, 0, 0, 0, 0, 0, 0, 0, 0, 0, 0, 0, 0, 0, 0, 0, 0, 0, 0, 0, 0, 0, 0, 0, 0, 0, 0, 0, 0, 0, 0, 0, 0, 0, 0, 0, 0, 0, 0, 161, 0, 161, 0, 0, 0, 0, 0, 0, 0, 0, 0, 0, 0, 0, 292, 293, 295, 296, 297, 0, 0, 0, 0, 0, 0, 0, 0, 0, 0, 289, 0, 0, 292, 293, 0, 289, 0, 0, 0, 0, 0, 0, 0, 0, 0, 0, 0, 0, 0, 161, 0, 161, 164, 165, 166, 0, 0, 0, 0, 0, 0, 0, 0, 0, 0, 0, 0, 0, 0, 0, 0, 0, 0, 0, 0, 0, 162, 0, 0, 0, 0, 0, 0, 0, 0, 0, 0, 0, 0, 0, 161, 0, 161, 163, 0, 0, 0, 0, 0, 0, 0, 0, 0, 0, 0, 0, 0, 0, 0, 0, 0, 0, 0, 0, 0, 0, 0, 0, 0, 0, 0, 0, 0, 162, 0, 0, 0, 0, 163, 0, 161, 0, 161, 0, 0, 0, 0, 0, 0, 0, 0, 0, 0, 0, 0, 0, 0, 0, 0, 0, 0, 0, 0, 161, 0, 0, 0, 0, 0, 0, 0, 0, 0, 0, 0, 0, 0, 0, 0, 0, 0, 0, 0, 0, 0, 0, 0, 0, 0, 0, 0, 0, 0, 0, 0],
         "height":18,
         "id":4,
         "name":"backgroundLayer",
         "opacity":1,
         "type":"tilelayer",
         "visible":true,
         "width":300,
         "x":0,
         "y":0
        }],
 "nextlayerid":7,
 "nextobjectid":97,
 "orientation":"orthogonal",
 "renderorder":"right-down",
 "tiledversion":"1.8.6",
 "tileheight":8,
 "tilesets":[
        {
         "columns":16,
         "firstgid":1,
         "image":"..\/tiles\/tiles.png",
         "imageheight":176,
         "imagewidth":128,
         "margin":0,
         "name":"tiles",
         "spacing":0,
         "tilecount":352,
         "tileheight":8,
         "tiles":[
                {
                 "id":3,
                 "properties":[
                        {
                         "name":"collide",
                         "type":"bool",
                         "value":true
                        }]
                }, 
                {
                 "id":4,
                 "properties":[
                        {
                         "name":"collide",
                         "type":"bool",
                         "value":true
                        }]
                }, 
                {
                 "id":5,
                 "properties":[
                        {
                         "name":"collide",
                         "type":"bool",
                         "value":true
                        }]
                }, 
                {
                 "id":16,
                 "properties":[
                        {
                         "name":"collide",
                         "type":"bool",
                         "value":true
                        }]
                }, 
                {
                 "id":24,
                 "properties":[
                        {
                         "name":"collide",
                         "type":"bool",
                         "value":true
                        }]
                }, 
                {
                 "id":26,
                 "properties":[
                        {
                         "name":"collide",
                         "type":"bool",
                         "value":true
                        }]
                }, 
                {
                 "id":32,
                 "properties":[
                        {
                         "name":"collide",
                         "type":"bool",
                         "value":true
                        }]
                }, 
                {
                 "id":33,
                 "properties":[
                        {
                         "name":"collide",
                         "type":"bool",
                         "value":true
                        }]
                }, 
                {
                 "id":84,
                 "properties":[
                        {
                         "name":"collide",
                         "type":"bool",
                         "value":true
                        }]
                }],
         "tilewidth":8
        }],
 "tilewidth":8,
 "type":"map",
 "version":"1.8",
 "width":300
}